Workbook

Sheet START HERE
A1: ServiceNow Architecture Discovery Workbook
A2: Purpose | B2: Learn an inherited ServiceNow instance by tracing real work, record what you can PROVE, and make unknowns and risks visible - with limited access. Companion to the Obsidian vault (same IDs, same vocabulary).
A4: PRINCIPLES
A5: ServiceNow is authoritative | B5: If this workbook disagrees with the platform, the platform wins until you resolve the difference. Update the workbook, set Last Reviewed.
A6: Never guess | B6: If you don't know why something exists, log it on the Unknowns sheet. Write 'UNKNOWN' in Purpose columns. Do not invent reasons.
A7: Document relationships | B7: A table name is less useful than knowing what depends on it. Use the Dependencies sheet and Impact Check.
A8: Business purpose first | B8: Link objects to a Business Process. If you cannot, say so.
A9: Track ownership and confidence | B9: Every Critical/High object should end with an owner. Every row has a Confidence level (High=verified, Medium=strongly supported, Low=inferred).
A10: Capture why | B10: Record decisions (and reconstructed decisions, labeled as such).
A11: Build incrementally | B11: Do not try to document the whole platform. Document what you encounter while tracing real processes.
A13: HOW TO USE (daily loop)
A14: 1. Architecture Overview | B14: Fill what you can verify. Everything else becomes an Unknown.
A15: 2. Inventory | B15: Add rows to Object Inventory (existence + owner + criticality) and Applications.
A16: 3. Pick processes | B16: Business Processes sheet: choose 3-5, set Priority to Trace.
A17: 4. Trace end-to-end | B17: User -> catalog -> variables -> flow -> tables -> scripts -> notifications -> approvals -> integrations -> reporting.
A18: 5. Document as you meet objects | B18: Use the detail sheet for the type (Tables, Flows, ...). Add an Object Inventory row for each.
A19: 6. Record relationships | B19: Dependencies sheet: Source -> relationship -> Target. Use exact object names.
A20: 7. Record Unknowns and Risks | B20: Never leave a question in your head. Set Access Needed - that builds your access case.
A21: 8. Validate with SMEs | B21: Set Confidence to High only when verified directly. Record who validated and when.
A22: 9. Check the Dashboard | B22: See coverage, owner gaps, critical risks. Update Current Focus.
A23: 10. Before any change | B23: Use Impact Check, then Decisions and Change History.
A25: SHEET MAP
A26: Dashboard | B26: Metrics (formulas)
A27: Architecture Overview | B27: Instance facts, people, layers
A28: Object Inventory | B28: Master list of everything important
A29: Applications / Tables / Fields | B29: Application and data model
A30: Catalog Items / Variables | B30: Service catalog
A31: Flows / Scripts & Rules | B31: Automation and code
A32: Integrations | B32: External connections
A33: Security | B33: Roles, groups, ACLs
A34: Business Processes | B34: The spine - start here for tracing
A35: Dependencies / Impact Check | B35: Relationships and 'what breaks if I change this?'
A36: Risks / Unknowns | B36: Risk register (auto score) and unknowns register
A37: Decisions / Change History | B37: The 'why' and what changed
... A41: Reference Lists | B41: Dropdown values and definitions
A43: LEGEND
A44: Yellow + italic rows | B44: FICTIONAL EXAMPLES (IDs start EX-). They show how to fill a row. Not your environment. Excluded from Dashboard.
A45: Yellow input cells | B45: Cells you edit on Dashboard / Impact Check.
A46: Grey/blue header | B46: Hover headers with a red triangle for tips.
A47: Rows 'Suspected' on Risks | B47: Hypotheses to check, not findings.
A49: ASSUMPTIONS (mine, not facts about your instance)
A50: - | B50: ServiceNow role names, ACLs and table access differ by instance. 'Typical access' text is a starting hypothesis; record the real role in Notes.
A51: - | B51: Examples (EX-...) are invented: no real configuration of yours is represented.
A52: - | B52: Table, field and menu names mentioned are common ServiceNow conventions; confirm in your instance.
A53: - | B53: Seeded Unknowns/Risks are common to inherited instances; only R-001/R-002 are stated facts from you.
A54: - | B54: Do not run background scripts or change production without authority; this workbook is for read-only discovery until your transition agreement says otherwise.

Sheet Dashboard
A1: ARCHITECTURE DASHBOARD - all values are formulas. Yellow cells are yours to edit. Example rows (IDs starting EX-) are excluded.
A3: FOCUS (edit)
A4: Current discovery focus | B4: (e.g., Process 1: ...)
A5: Next discovery target | B5: (e.g., ...)
A6: 30-day plan days done | B6: ='30-Day Plan'!M2 -> 0 / 30
A8: INVENTORY & COVERAGE
A9: Metric | B9: Discovered | C9: Documented | D9: % Documented
A10: Total objects (Object Inventory) | B10: =SUMPRODUCT(('Object Inventory'!$A$3:$A$502<>"")*(LEFT('Object Inventory'!$A$3:$A$502,3)<>"EX-")) -> 0 | C10: =SUMPRODUCT(('Object Inventory'!$A$3:$A$502<>"")*(LEFT('Object Inventory'!$A$3:$A$502,3)<>"EX-")*(('Object Inventory'!$O$3:$O$502="Documented")+('Object Inventory'!$O$3:$O$502="Validated"))) -> 0 | D10: =IF(B10=0,0,C10/B10) -> 0
A11: Tables | B11: =SUMPRODUCT((Tables!$A$3:$A$502<>"")*(LEFT(Tables!$A$3:$A$502,3)<>"EX-")) -> 0 | C11: =SUMPRODUCT((Tables!$A$3:$A$502<>"")*(LEFT(Tables!$A$3:$A$502,3)<>"EX-")*((Tables!$AY$3:$AY$502="Documented")+(Tables!$AY$3:$AY$502="Validated"))) -> 0 | D11: =IF(B11=0,0,C11/B11) -> 0
A12: Flows / Subflows | B12: =SUMPRODUCT((Flows!$A$3:$A$502<>"")*(LEFT(Flows!$A$3:$A$502,3)<>"EX-")) -> 0 | C12: =SUMPRODUCT((Flows!$A$3:$A$502<>"")*(LEFT(Flows!$A$3:$A$502,3)<>"EX-")*((Flows!$AI$3:$AI$502="Documented")+(Flows!$AI$3:$AI$502="Validated"))) -> 0 | D12: =IF(B12=0,0,C12/B12) -> 0
A13: Catalog items | B13: =SUMPRODUCT(('Catalog Items'!$A$3:$A$502<>"")*(LEFT('Catalog Items'!$A$3:$A$502,3)<>"EX-")) -> 0 | C13: =SUMPRODUCT(('Catalog Items'!$A$3:$A$502<>"")*(LEFT('Catalog Items'!$A$3:$A$502,3)<>"EX-")*(('Catalog Items'!$AB$3:$AB$502="Documented")+('Catalog Items'!$AB$3:$AB$502="Validated"))) -> 0 | D13: =IF(B13=0,0,C13/B13) -> 0
A14: Integrations | B14: =SUMPRODUCT((Integrations!$A$3:$A$502<>"")*(LEFT(Integrations!$A$3:$A$502,3)<>"EX-")) -> 0 | C14: =SUMPRODUCT((Integrations!$A$3:$A$502<>"")*(LEFT(Integrations!$A$3:$A$502,3)<>"EX-")*((Integrations!$AD$3:$AD$502="Documented")+(Integrations!$AD$3:$AD$502="Validated"))) -> 0 | D14: =IF(B14=0,0,C14/B14) -> 0
A15: Business processes | B15: =SUMPRODUCT(('Business Processes'!$A$3:$A$502<>"")*(LEFT('Business Processes'!$A$3:$A$502,3)<>"EX-")) -> 0 | C15: =SUMPRODUCT(('Business Processes'!$A$3:$A$502<>"")*(LEFT('Business Processes'!$A$3:$A$502,3)<>"EX-")*(('Business Processes'!$AC$3:$AC$502="Documented")+('Business Processes'!$AC$3:$AC$502="Validated"))) -> 0 | D15: =IF(B15=0,0,C15/B15) -> 0
A16: Scripts & rules | B16: =SUMPRODUCT(('Scripts & Rules'!$A$3:$A$502<>"")*(LEFT('Scripts & Rules'!$A$3:$A$502,3)<>"EX-")) -> 0 | C16: =SUMPRODUCT(('Scripts & Rules'!$A$3:$A$502<>"")*(LEFT('Scripts & Rules'!$A$3:$A$502,3)<>"EX-")*(('Scripts & Rules'!$AA$3:$AA$502="Documented")+('Scripts & Rules'!$AA$3:$AA$502="Validated"))) -> 0 | D16: =IF(B16=0,0,C16/B16) -> 0
A17: Security (roles/groups/ACLs) | B17: =SUMPRODUCT((Security!$A$3:$A$502<>"")*(LEFT(Security!$A$3:$A$502,3)<>"EX-")) -> 0 | C17: =SUMPRODUCT((Security!$A$3:$A$502<>"")*(LEFT(Security!$A$3:$A$502,3)<>"EX-")*((Security!$W$3:$W$502="Documented")+(Security!$W$3:$W$502="Validated"))) -> 0 | D17: =IF(B17=0,0,C17/B17) -> 0
A18: Applications | B18: =SUMPRODUCT((Applications!$A$3:$A$502<>"")*(LEFT(Applications!$A$3:$A$502,3)<>"EX-")) -> 0 | C18: =SUMPRODUCT((Applications!$A$3:$A$502<>"")*(LEFT(Applications!$A$3:$A$502,3)<>"EX-")*((Applications!$O$3:$O$502="Documented")+(Applications!$O$3:$O$502="Validated"))) -> 0 | D18: =IF(B18=0,0,C18/B18) -> 0
A19: Fields (tracked) | B19: =SUMPRODUCT((Fields!$A$3:$A$502<>"")*(LEFT(Fields!$A$3:$A$502,3)<>"EX-")) -> 0 | C19: =SUMPRODUCT((Fields!$A$3:$A$502<>"")*(LEFT(Fields!$A$3:$A$502,3)<>"EX-")*((Fields!$W$3:$W$502="Documented")+(Fields!$W$3:$W$502="Validated"))) -> 0 | D19: =IF(B19=0,0,C19/B19) -> 0
A20: Variables (tracked) | B20: =SUMPRODUCT((Variables!$A$3:$A$502<>"")*(LEFT(Variables!$A$3:$A$502,3)<>"EX-")) -> 0 | C20: =SUMPRODUCT((Variables!$A$3:$A$502<>"")*(LEFT(Variables!$A$3:$A$502,3)<>"EX-")*((Variables!$R$3:$R$502="Documented")+(Variables!$R$3:$R$502="Validated"))) -> 0 | D20: =IF(B20=0,0,C20/B20) -> 0
A21: OVERALL DOCUMENTATION % (Object Inventory) | D21: =D10 -> 0
A23: RISKS & UNKNOWNS (open items only)
A24: Critical risks | B24: =SUMPRODUCT((Risks!$A$3:$A$502<>"")*(LEFT(Risks!$A$3:$A$502,3)<>"EX-")*(Risks!$I$3:$I$502="Critical")*(Risks!$L$3:$L$502<>"Closed")*(Risks!$L$3:$L$502<>"Accepted")) -> 1
A25: High risks | B25: =SUMPRODUCT((Risks!$A$3:$A$502<>"")*(LEFT(Risks!$A$3:$A$502,3)<>"EX-")*(Risks!$I$3:$I$502="High")*(Risks!$L$3:$L$502<>"Closed")*(Risks!$L$3:$L$502<>"Accepted")) -> 1
A26: Suspected risks still to verify | B26: =SUMPRODUCT((Risks!$A$3:$A$502<>"")*(LEFT(Risks!$A$3:$A$502,3)<>"EX-")*(Risks!$L$3:$L$502="Suspected")) -> 16
A27: Critical unknowns (unresolved) | B27: =SUMPRODUCT((Unknowns!$A$3:$A$502<>"")*(LEFT(Unknowns!$A$3:$A$502,3)<>"EX-")*(Unknowns!$I$3:$I$502="Critical")*(Unknowns!$J$3:$J$502<>"Resolved")*(Unknowns!$J$3:$J$502<>"Closed - Not Resolvable")) -> 6
A28: High unknowns (unresolved) | B28: =SUMPRODUCT((Unknowns!$A$3:$A$502<>"")*(LEFT(Unknowns!$A$3:$A$502,3)<>"EX-")*(Unknowns!$I$3:$I$502="High")*(Unknowns!$J$3:$J$502<>"Resolved")*(Unknowns!$J$3:$J$502<>"Closed - Not Resolvable")) -> 5
A29: All unresolved unknowns | B29: =SUMPRODUCT((Unknowns!$A$3:$A$502<>"")*(LEFT(Unknowns!$A$3:$A$502,3)<>"EX-")*(Unknowns!$J$3:$J$502<>"Resolved")*(Unknowns!$J$3:$J$502<>"Closed - Not Resolvable")) -> 12
A30: Unknowns blocked by access | B30: =SUMPRODUCT((Unknowns!$A$3:$A$502<>"")*(LEFT(Unknowns!$A$3:$A$502,3)<>"EX-")*(Unknowns!$J$3:$J$502="Blocked - Needs Access")) -> 0 | F30: Use these to justify access requests
A32: OWNERSHIP & CUSTOMIZATION (Object Inventory)
A33: Undocumented customizations (Custom or Customized OOTB, not Documented/Validated) | B33: =SUMPRODUCT(('Object Inventory'!$A$3:$A$502<>"")*(LEFT('Object Inventory'!$A$3:$A$502,3)<>"EX-")*((('Object Inventory'!$M$3:$M$502="Custom")+('Object Inventory'!$M$3:$M$502="Customized OOTB"))>0)*(1-(('Object Inventory'!$O$3:$O$502="Documented")+('Object Inventory'!$O$3:$O$502="Validated")))) -> 0
A34: Objects with no owner (neither business nor technical) | B34: =SUMPRODUCT(('Object Inventory'!$A$3:$A$502<>"")*(LEFT('Object Inventory'!$A$3:$A$502,3)<>"EX-")*('Object Inventory'!$I$3:$I$502="")*('Object Inventory'!$J$3:$J$502="")) -> 0
A35: Objects with no technical owner | B35: =SUMPRODUCT(('Object Inventory'!$A$3:$A$502<>"")*(LEFT('Object Inventory'!$A$3:$A$502,3)<>"EX-")*('Object Inventory'!$J$3:$J$502="")) -> 0
A36: Low or Unknown confidence objects | B36: =SUMPRODUCT(('Object Inventory'!$A$3:$A$502<>"")*(LEFT('Object Inventory'!$A$3:$A$502,3)<>"EX-")*((('Object Inventory'!$P$3:$P$502="Low")+('Object Inventory'!$P$3:$P$502="Unknown")+('Object Inventory'!$P$3:$P$502=""))>0)) -> 0
A37: Critical objects not yet Documented/Validated | B37: =SUMPRODUCT(('Object Inventory'!$A$3:$A$502<>"")*(LEFT('Object Inventory'!$A$3:$A$502,3)<>"EX-")*('Object Inventory'!$N$3:$N$502="Critical")*(1-(('Object Inventory'!$O$3:$O$502="Documented")+('Object Inventory'!$O$3:$O$502="Validated")))) -> 0
A38: Dependency rows recorded | B38: =SUMPRODUCT((Dependencies!$A$3:$A$502<>"")*(LEFT(Dependencies!$A$3:$A$502,3)<>"EX-")) -> 0
A39: Example rows still present (all sheets) | B39: =SUMPRODUCT(--(LEFT('Object Inventory'!$A$3:$A$502,3)="EX-"))+SUMPRODUCT(--(LEFT(Tables!$A$3:$A$502,3)="EX-"))+SUMPRODUCT(--(LEFT(Flows!$A$3:$A$502,3)="EX-"))+SUMPRODUCT(--(LEFT('Catalog Items'!$A$3:$A$502,3)="EX-"))+SUMPRODUCT(--(LEFT(Integrations!$A$3:$A$502,3)="EX-"))+SUMPRODUCT(--(LEFT('Scripts & Rules'!$A$3:$A$502,3)="EX-"))+SUMPRODUCT(--(LEFT(Dependencies!$A$3:$A$502,3)="EX-"))+SUMPRODUCT(--(LEFT(Risks!$A$3:$A$502,3)="EX-"))+SUMPRODUCT(--(LEFT(Unknowns!$A$3:$A$502,3)="EX-")) -> 22 | F39: Fictional; delete when ready
A41: OBJECTS BY TYPE (Object Inventory)
A42: Object Type | B42: Discovered | C42: Documented | D42: % Documented | E42: No Owner
A43: Table | B43: =SUMPRODUCT(('Object Inventory'!$A$3:$A$502<>"")*(LEFT('Object Inventory'!$A$3:$A$502,3)<>"EX-")*('Object Inventory'!$D$3:$D$502=A43)) -> 0 | C43: =SUMPRODUCT(('Object Inventory'!$A$3:$A$502<>"")*(LEFT('Object Inventory'!$A$3:$A$502,3)<>"EX-")*('Object Inventory'!$D$3:$D$502=A43)*(('Object Inventory'!$O$3:$O$502="Documented")+('Object Inventory'!$O$3:$O$502="Validated"))) -> 0 | D43: =IF(B43=0,"",C43/B43) | E43: =SUMPRODUCT(('Object Inventory'!$A$3:$A$502<>"")*(LEFT('Object Inventory'!$A$3:$A$502,3)<>"EX-")*('Object Inventory'!$D$3:$D$502=A43)*('Object Inventory'!$I$3:$I$502="")*('Object Inventory'!$J$3:$J$502="")) -> 0
A44: Field | B44: =SUMPRODUCT(('Object Inventory'!$A$3:$A$502<>"")*(LEFT('Object Inventory'!$A$3:$A$502,3)<>"EX-")*('Object Inventory'!$D$3:$D$502=A44)) -> 0 | C44: =SUMPRODUCT(('Object Inventory'!$A$3:$A$502<>"")*(LEFT('Object Inventory'!$A$3:$A$502,3)<>"EX-")*('Object Inventory'!$D$3:$D$502=A44)*(('Object Inventory'!$O$3:$O$502="Documented")+('Object Inventory'!$O$3:$O$502="Validated"))) -> 0 | D44: =IF(B44=0,"",C44/B44) | E44: =SUMPRODUCT(('Object Inventory'!$A$3:$A$502<>"")*(LEFT('Object Inventory'!$A$3:$A$502,3)<>"EX-")*('Object Inventory'!$D$3:$D$502=A44)*('Object Inventory'!$I$3:$I$502="")*('Object Inventory'!$J$3:$J$502="")) -> 0
A45: Application | B45: =SUMPRODUCT(('Object Inventory'!$A$3:$A$502<>"")*(LEFT('Object Inventory'!$A$3:$A$502,3)<>"EX-")*('Object Inventory'!$D$3:$D$502=A45)) -> 0 | C45: =SUMPRODUCT(('Object Inventory'!$A$3:$A$502<>"")*(LEFT('Object Inventory'!$A$3:$A$502,3)<>"EX-")*('Object Inventory'!$D$3:$D$502=A45)*(('Object Inventory'!$O$3:$O$502="Documented")+('Object Inventory'!$O$3:$O$502="Validated"))) -> 0 | D45: =IF(B45=0,"",C45/B45) | E45: =SUMPRODUCT(('Object Inventory'!$A$3:$A$502<>"")*(LEFT('Object Inventory'!$A$3:$A$502,3)<>"EX-")*('Object Inventory'!$D$3:$D$502=A45)*('Object Inventory'!$I$3:$I$502="")*('Object Inventory'!$J$3:$J$502="")) -> 0
A46: Module | B46: =SUMPRODUCT(('Object Inventory'!$A$3:$A$502<>"")*(LEFT('Object Inventory'!$A$3:$A$502,3)<>"EX-")*('Object Inventory'!$D$3:$D$502=A46)) -> 0 | C46: =SUMPRODUCT(('Object Inventory'!$A$3:$A$502<>"")*(LEFT('Object Inventory'!$A$3:$A$502,3)<>"EX-")*('Object Inventory'!$D$3:$D$502=A46)*(('Object Inventory'!$O$3:$O$502="Documented")+('Object Inventory'!$O$3:$O$502="Validated"))) -> 0 | D46: =IF(B46=0,"",C46/B46) | E46: =SUMPRODUCT(('Object Inventory'!$A$3:$A$502<>"")*(LEFT('Object Inventory'!$A$3:$A$502,3)<>"EX-")*('Object Inventory'!$D$3:$D$502=A46)*('Object Inventory'!$I$3:$I$502="")*('Object Inventory'!$J$3:$J$502="")) -> 0
A47: Flow | B47: =SUMPRODUCT(('Object Inventory'!$A$3:$A$502<>"")*(LEFT('Object Inventory'!$A$3:$A$502,3)<>"EX-")*('Object Inventory'!$D$3:$D$502=A47)) -> 0 | C47: =SUMPRODUCT(('Object Inventory'!$A$3:$A$502<>"")*(LEFT('Object Inventory'!$A$3:$A$502,3)<>"EX-")*('Object Inventory'!$D$3:$D$502=A47)*(('Object Inventory'!$O$3:$O$502="Documented")+('Object Inventory'!$O$3:$O$502="Validated"))) -> 0 | D47: =IF(B47=0,"",C47/B47) | E47: =SUMPRODUCT(('Object Inventory'!$A$3:$A$502<>"")*(LEFT('Object Inventory'!$A$3:$A$502,3)<>"EX-")*('Object Inventory'!$D$3:$D$502=A47)*('Object Inventory'!$I$3:$I$502="")*('Object Inventory'!$J$3:$J$502="")) -> 0
A48: Subflow | B48: =SUMPRODUCT(('Object Inventory'!$A$3:$A$502<>"")*(LEFT('Object Inventory'!$A$3:$A$502,3)<>"EX-")*('Object Inventory'!$D$3:$D$502=A48)) -> 0 | C48: =SUMPRODUCT(('Object Inventory'!$A$3:$A$502<>"")*(LEFT('Object Inventory'!$A$3:$A$502,3)<>"EX-")*('Object Inventory'!$D$3:$D$502=A48)*(('Object Inventory'!$O$3:$O$502="Documented")+('Object Inventory'!$O$3:$O$502="Validated"))) -> 0 | D48: =IF(B48=0,"",C48/B48) | E48: =SUMPRODUCT(('Object Inventory'!$A$3:$A$502<>"")*(LEFT('Object Inventory'!$A$3:$A$502,3)<>"EX-")*('Object Inventory'!$D$3:$D$502=A48)*('Object Inventory'!$I$3:$I$502="")*('Object Inventory'!$J$3:$J$502="")) -> 0
A49: Flow Action | B49: =SUMPRODUCT(('Object Inventory'!$A$3:$A$502<>"")*(LEFT('Object Inventory'!$A$3:$A$502,3)<>"EX-")*('Object Inventory'!$D$3:$D$502=A49)) -> 0 | C49: =SUMPRODUCT(('Object Inventory'!$A$3:$A$502<>"")*(LEFT('Object Inventory'!$A$3:$A$502,3)<>"EX-")*('Object Inventory'!$D$3:$D$502=A49)*(('Object Inventory'!$O$3:$O$502="Documented")+('Object Inventory'!$O$3:$O$502="Validated"))) -> 0 | D49: =IF(B49=0,"",C49/B49) | E49: =SUMPRODUCT(('Object Inventory'!$A$3:$A$502<>"")*(LEFT('Object Inventory'!$A$3:$A$502,3)<>"EX-")*('Object Inventory'!$D$3:$D$502=A49)*('Object Inventory'!$I$3:$I$502="")*('Object Inventory'!$J$3:$J$502="")) -> 0
A50: Business Rule | B50: =SUMPRODUCT(('Object Inventory'!$A$3:$A$502<>"")*(LEFT('Object Inventory'!$A$3:$A$502,3)<>"EX-")*('Object Inventory'!$D$3:$D$502=A50)) -> 0 | C50: =SUMPRODUCT(('Object Inventory'!$A$3:$A$502<>"")*(LEFT('Object Inventory'!$A$3:$A$502,3)<>"EX-")*('Object Inventory'!$D$3:$D$502=A50)*(('Object Inventory'!$O$3:$O$502="Documented")+('Object Inventory'!$O$3:$O$502="Validated"))) -> 0 | D50: =IF(B50=0,"",C50/B50) | E50: =SUMPRODUCT(('Object Inventory'!$A$3:$A$502<>"")*(LEFT('Object Inventory'!$A$3:$A$502,3)<>"EX-")*('Object Inventory'!$D$3:$D$502=A50)*('Object Inventory'!$I$3:$I$502="")*('Object Inventory'!$J$3:$J$502="")) -> 0
A51: Client Script | B51: =SUMPRODUCT(('Object Inventory'!$A$3:$A$502<>"")*(LEFT('Object Inventory'!$A$3:$A$502,3)<>"EX-")*('Object Inventory'!$D$3:$D$502=A51)) -> 0 | C51: =SUMPRODUCT(('Object Inventory'!$A$3:$A$502<>"")*(LEFT('Object Inventory'!$A$3:$A$502,3)<>"EX-")*('Object Inventory'!$D$3:$D$502=A51)*(('Object Inventory'!$O$3:$O$502="Documented")+('Object Inventory'!$O$3:$O$502="Validated"))) -> 0 | D51: =IF(B51=0,"",C51/B51) | E51: =SUMPRODUCT(('Object Inventory'!$A$3:$A$502<>"")*(LEFT('Object Inventory'!$A$3:$A$502,3)<>"EX-")*('Object Inventory'!$D$3:$D$502=A51)*('Object Inventory'!$I$3:$I$502="")*('Object Inventory'!$J$3:$J$502="")) -> 0
A52: UI Policy | B52: =SUMPRODUCT(('Object Inventory'!$A$3:$A$502<>"")*(LEFT('Object Inventory'!$A$3:$A$502,3)<>"EX-")*('Object Inventory'!$D$3:$D$502=A52)) -> 0 | C52: =SUMPRODUCT(('Object Inventory'!$A$3:$A$502<>"")*(LEFT('Object Inventory'!$A$3:$A$502,3)<>"EX-")*('Object Inventory'!$D$3:$D$502=A52)*(('Object Inventory'!$O$3:$O$502="Documented")+('Object Inventory'!$O$3:$O$502="Validated"))) -> 0 | D52: =IF(B52=0,"",C52/B52) | E52: =SUMPRODUCT(('Object Inventory'!$A$3:$A$502<>"")*(LEFT('Object Inventory'!$A$3:$A$502,3)<>"EX-")*('Object Inventory'!$D$3:$D$502=A52)*('Object Inventory'!$I$3:$I$502="")*('Object Inventory'!$J$3:$J$502="")) -> 0
A53: UI Action | B53: =SUMPRODUCT(('Object Inventory'!$A$3:$A$502<>"")*(LEFT('Object Inventory'!$A$3:$A$502,3)<>"EX-")*('Object Inventory'!$D$3:$D$502=A53)) -> 0 | C53: =SUMPRODUCT(('Object Inventory'!$A$3:$A$502<>"")*(LEFT('Object Inventory'!$A$3:$A$502,3)<>"EX-")*('Object Inventory'!$D$3:$D$502=A53)*(('Object Inventory'!$O$3:$O$502="Documented")+('Object Inventory'!$O$3:$O$502="Validated"))) -> 0 | D53: =IF(B53=0,"",C53/B53) | E53: =SUMPRODUCT(('Object Inventory'!$A$3:$A$502<>"")*(LEFT('Object Inventory'!$A$3:$A$502,3)<>"EX-")*('Object Inventory'!$D$3:$D$502=A53)*('Object Inventory'!$I$3:$I$502="")*('Object Inventory'!$J$3:$J$502="")) -> 0
A54: Script Include | B54: =SUMPRODUCT(('Object Inventory'!$A$3:$A$502<>"")*(LEFT('Object Inventory'!$A$3:$A$502,3)<>"EX-")*('Object Inventory'!$D$3:$D$502=A54)) -> 0 | C54: =SUMPRODUCT(('Object Inventory'!$A$3:$A$502<>"")*(LEFT('Object Inventory'!$A$3:$A$502,3)<>"EX-")*('Object Inventory'!$D$3:$D$502=A54)*(('Object Inventory'!$O$3:$O$502="Documented")+('Object Inventory'!$O$3:$O$502="Validated"))) -> 0 | D54: =IF(B54=0,"",C54/B54) | E54: =SUMPRODUCT(('Object Inventory'!$A$3:$A$502<>"")*(LEFT('Object Inventory'!$A$3:$A$502,3)<>"EX-")*('Object Inventory'!$D$3:$D$502=A54)*('Object Inventory'!$I$3:$I$502="")*('Object Inventory'!$J$3:$J$502="")) -> 0
... A73: Other | B73: =SUMPRODUCT(('Object Inventory'!$A$3:$A$502<>"")*(LEFT('Object Inventory'!$A$3:$A$502,3)<>"EX-")*('Object Inventory'!$D$3:$D$502=A73)) -> 0 | C73: =SUMPRODUCT(('Object Inventory'!$A$3:$A$502<>"")*(LEFT('Object Inventory'!$A$3:$A$502,3)<>"EX-")*('Object Inventory'!$D$3:$D$502=A73)*(('Object Inventory'!$O$3:$O$502="Documented")+('Object Inventory'!$O$3:$O$502="Validated"))) -> 0 | D73: =IF(B73=0,"",C73/B73) | E73: =SUMPRODUCT(('Object Inventory'!$A$3:$A$502<>"")*(LEFT('Object Inventory'!$A$3:$A$502,3)<>"EX-")*('Object Inventory'!$D$3:$D$502=A73)*('Object Inventory'!$I$3:$I$502="")*('Object Inventory'!$J$3:$J$502="")) -> 0

Sheet Architecture Overview
A1: ARCHITECTURE OVERVIEW - the front page of your instance. Fill what you can verify; leave the rest blank and log an Unknown. Do not guess.
A2: Item | B2: Value | C2: Evidence / Source | D2: Confidence | E2: Last Verified | F2: Notes / Linked Unknown ID
A3: INSTANCE
A4: Instance name | D4: Unknown
A5: Instance URL (production) | D5: Unknown
A6: Sub-production instance(s) and URLs | D6: Unknown
A7: Production / sub-production (this record is for) | D7: Unknown
A8: ServiceNow version / release | D8: Unknown
A9: Last upgrade (date) | D9: Unknown
A10: Next planned upgrade (date) | D10: Unknown
A11: Upgrade owner | D11: Unknown
A12: PEOPLE
A13: Platform owner | D13: Unknown
A14: Primary administrator | D14: Unknown
A15: Backup administrator | D15: Unknown
A16: Technical owner | D16: Unknown
A17: Business owner | D17: Unknown
A18: Vendor / partner support | D18: Unknown
A19: Now Support authorized contacts | D19: Unknown
A20: Security contact | D20: Unknown
A21: WHAT IS ON THE PLATFORM
A22: Major applications (see Applications sheet) | D22: Unknown
A23: Major modules | D23: Unknown
A24: Major business processes (see Business Processes sheet) | D24: Unknown
A25: Major external systems | D25: Unknown
A26: Major integrations (see Integrations sheet) | D26: Unknown
A27: Major customizations | D27: Unknown
A28: Critical platform dependencies (SSO, MID, email, external APIs) | D28: Unknown
A29: PROCESS & GOVERNANCE
A30: How changes move to production | D30: Unknown
A31: Change approval process | D31: Unknown
A32: Existing documentation location | D32: Unknown
A33: Testing approach (ATF / manual) | D33: Unknown
A34: Monitoring / alerting in place | D34: Unknown
A35: Architecture diagram location (Obsidian: 01 - PLATFORM/Diagram Library) | D35: Unknown
A37: ARCHITECTURE LAYERS (live counts from your sheets; examples excluded)
A38: Layer | B38: Where documented | C38: Rows recorded | D38: Documented / Validated
A39: Applications | B39: Applications | C39: =SUMPRODUCT((Applications!$A$3:$A$502<>"")*(LEFT(Applications!$A$3:$A$502,3)<>"EX-")) -> 0 | D39: =SUMPRODUCT((Applications!$A$3:$A$502<>"")*(LEFT(Applications!$A$3:$A$502,3)<>"EX-")*((Applications!$O$3:$O$502="Documented")+(Applications!$O$3:$O$502="Validated"))) -> 0
A40: Data Model (Tables) | B40: Tables | C40: =SUMPRODUCT((Tables!$A$3:$A$502<>"")*(LEFT(Tables!$A$3:$A$502,3)<>"EX-")) -> 0 | D40: =SUMPRODUCT((Tables!$A$3:$A$502<>"")*(LEFT(Tables!$A$3:$A$502,3)<>"EX-")*((Tables!$AY$3:$AY$502="Documented")+(Tables!$AY$3:$AY$502="Validated"))) -> 0
A41: Service Catalog | B41: Catalog Items | C41: =SUMPRODUCT(('Catalog Items'!$A$3:$A$502<>"")*(LEFT('Catalog Items'!$A$3:$A$502,3)<>"EX-")) -> 0 | D41: =SUMPRODUCT(('Catalog Items'!$A$3:$A$502<>"")*(LEFT('Catalog Items'!$A$3:$A$502,3)<>"EX-")*(('Catalog Items'!$AB$3:$AB$502="Documented")+('Catalog Items'!$AB$3:$AB$502="Validated"))) -> 0
A42: Automation (Flows) | B42: Flows | C42: =SUMPRODUCT((Flows!$A$3:$A$502<>"")*(LEFT(Flows!$A$3:$A$502,3)<>"EX-")) -> 0 | D42: =SUMPRODUCT((Flows!$A$3:$A$502<>"")*(LEFT(Flows!$A$3:$A$502,3)<>"EX-")*((Flows!$AI$3:$AI$502="Documented")+(Flows!$AI$3:$AI$502="Validated"))) -> 0
A43: Scripts & Rules | B43: Scripts & Rules | C43: =SUMPRODUCT(('Scripts & Rules'!$A$3:$A$502<>"")*(LEFT('Scripts & Rules'!$A$3:$A$502,3)<>"EX-")) -> 0 | D43: =SUMPRODUCT(('Scripts & Rules'!$A$3:$A$502<>"")*(LEFT('Scripts & Rules'!$A$3:$A$502,3)<>"EX-")*(('Scripts & Rules'!$AA$3:$AA$502="Documented")+('Scripts & Rules'!$AA$3:$AA$502="Validated"))) -> 0
A44: Integrations | B44: Integrations | C44: =SUMPRODUCT((Integrations!$A$3:$A$502<>"")*(LEFT(Integrations!$A$3:$A$502,3)<>"EX-")) -> 0 | D44: =SUMPRODUCT((Integrations!$A$3:$A$502<>"")*(LEFT(Integrations!$A$3:$A$502,3)<>"EX-")*((Integrations!$AD$3:$AD$502="Documented")+(Integrations!$AD$3:$AD$502="Validated"))) -> 0
A45: Security | B45: Security | C45: =SUMPRODUCT((Security!$A$3:$A$502<>"")*(LEFT(Security!$A$3:$A$502,3)<>"EX-")) -> 0 | D45: =SUMPRODUCT((Security!$A$3:$A$502<>"")*(LEFT(Security!$A$3:$A$502,3)<>"EX-")*((Security!$W$3:$W$502="Documented")+(Security!$W$3:$W$502="Validated"))) -> 0
A46: Business Processes | B46: Business Processes | C46: =SUMPRODUCT(('Business Processes'!$A$3:$A$502<>"")*(LEFT('Business Processes'!$A$3:$A$502,3)<>"EX-")) -> 0 | D46: =SUMPRODUCT(('Business Processes'!$A$3:$A$502<>"")*(LEFT('Business Processes'!$A$3:$A$502,3)<>"EX-")*(('Business Processes'!$AC$3:$AC$502="Documented")+('Business Processes'!$AC$3:$AC$502="Validated"))) -> 0
A47: Reporting / Portals / UI | B47: Object Inventory (types Report, Dashboard, Widget, Portal) | C47: =SUMPRODUCT(('Object Inventory'!$A$3:$A$502<>"")*(LEFT('Object Inventory'!$A$3:$A$502,3)<>"EX-")*((('Object Inventory'!$D$3:$D$502="Report")+('Object Inventory'!$D$3:$D$502="Dashboard")+('Object Inventory'!$D$3:$D$502="Widget")+('Object Inventory'!$D$3:$D$502="Portal"))>0)) -> 0 | D47: =SUMPRODUCT(('Object Inventory'!$A$3:$A$502<>"")*(LEFT('Object Inventory'!$A$3:$A$502,3)<>"EX-")*((('Object Inventory'!$D$3:$D$502="Report")+('Object Inventory'!$D$3:$D$502="Dashboard")+('Object Inventory'!$D$3:$D$502="Widget")+('Object Inventory'!$D$3:$D$502="Portal"))>0)*(('Object Inventory'!$O$3:$O$502="Documented")+('Object Inventory'!$O$3:$O$502="Validated"))) -> 0

Sheet Object Inventory
A1: MASTER OBJECT INVENTORY - one row per important object. Row = 'it exists'. Detail sheets/notes = 'how it works'. Examples are yellow/italic (IDs start EX-) and are excluded from Dashboard counts.
A2: Object ID | B2: Object Name | C2: Display Name | D2: Object Type | E2: Application | F2: Scope | G2: Purpose | H2: Business Process | I2: Business Owner | J2: Technical Owner | K2: Status | L2: Active/Inactive | M2: OOTB/Custom | N2: Criticality | O2: Documentation Status | P2: Confidence | Q2: Dependencies | R2: Dependents | S2: Related Objects | T2: Last Reviewed | U2: Access Needed | V2: sys_id / Link | W2: Detail Lives In | X2: Notes
A3: EX-OBJ-001 | B3: u_ex_asset_request | C3: Asset Request | D3: Table | E3: EXAMPLE Asset Requests | F3: x_ex_assetreq | G3: Stores each laptop/asset request | H3: EXAMPLE Laptop Request | K3: In Use | L3: Active | M3: Custom | N3: Critical | O3: Documented | P3: High | Q3: EX Laptop Request Fulfillment (updates) | R3: EX Set Cost Center Default; EX ACL write | U3: Elevated Application | W3: Tables | X3: EXAMPLE - FICTIONAL. Not part of your environment. Delete when you no longer need it.
A4: EX-OBJ-002 | B4: EX Laptop Request | C4: Laptop Request | D4: Catalog Item | E4: EXAMPLE Asset Requests | F4: x_ex_assetreq | G4: Employee-facing request form | H4: EXAMPLE Laptop Request | K4: In Use | L4: Active | M4: Custom | N4: High | O4: Documented | P4: High | Q4: EX Laptop Request Fulfillment | R4: Employees (portal) | U4: Basic User | W4: Catalog Items | X4: EXAMPLE - FICTIONAL. Not part of your environment. Delete when you no longer need it.
A5: EX-OBJ-003 | B5: EX Laptop Request Fulfillment | C5: Laptop Request Fulfillment | D5: Flow | E5: EXAMPLE Asset Requests | F5: x_ex_assetreq | G5: Approval, task creation, record updates | H5: EXAMPLE Laptop Request | K5: In Use | L5: Active | M5: Custom | N5: Critical | O5: Partially Documented | P5: Medium | Q5: EX Get Manager Approval; u_ex_asset_request; EX HR Employee Lookup | R5: EX Laptop Request | U5: Admin | W5: Flows | X5: EXAMPLE - FICTIONAL. Not part of your environment. Delete when you no longer need it.
A6: EX-OBJ-004 | B6: EX Set Cost Center Default | C6: Set Cost Center Default | D6: Business Rule | E6: EXAMPLE Asset Requests | F6: x_ex_assetreq | G6: UNKNOWN - see EX-U-001 | H6: EXAMPLE Laptop Request | K6: In Use | L6: Active | M6: Custom | N6: Medium | O6: Discovered | P6: Low | Q6: EXCostCenterUtil | R6: u_ex_asset_request inserts | U6: Admin | W6: Scripts & Rules | X6: EXAMPLE - FICTIONAL. Not part of your environment. Delete when you no longer need it.
A7: EX-OBJ-005 | B7: EX HR Employee Lookup | C7: HR Employee Lookup | D7: Integration | E7: EXAMPLE Integrations | F7: global | G7: Looks up employee data in a (fictional) HR system | H7: EXAMPLE Laptop Request | K7: In Use | L7: Active | M7: Custom | N7: High | O7: Partially Documented | P7: Low | Q7: External HR system | R7: EX Laptop Request Fulfillment | U7: Admin | W7: Integrations | X7: EXAMPLE - FICTIONAL. Not part of your environment. Delete when you no longer need it.
A8: EX-OBJ-006 | B8: x_ex_assetreq.fulfiller | C8: Asset Fulfiller | D8: Role | E8: EXAMPLE Asset Requests | F8: x_ex_assetreq | G8: Lets fulfillers work asset requests | K8: In Use | L8: Active | M8: Custom | N8: Medium | O8: Documented | P8: Medium | R8: EX ACL write u_ex_asset_request | U8: Admin | W8: Security | X8: EXAMPLE - FICTIONAL. Not part of your environment. Delete when you no longer need it.

Sheet Applications
A1: APPLICATIONS & MODULES - what is installed/used and why. Start here for Days 4-5 of the plan.
A2: App ID | B2: Application Name | C2: Scope | D2: Source (OOTB / Store / Custom) | E2: Version | F2: Active | G2: Purpose | H2: Business Owner | I2: Technical Owner | J2: Key Modules | K2: Key Tables | L2: Key Business Processes | M2: Primary Users / Groups | N2: Criticality | O2: Documentation Status | P2: Confidence | Q2: Evidence / Source | R2: Access Needed | S2: Last Reviewed | T2: Notes
A3: EX-APP-001 | B3: EXAMPLE Asset Requests | C3: x_ex_assetreq | D3: Custom | E3: 1.2 | F3: Active | G3: Employee asset requests | J3: Request Asset; Fulfill Asset | K3: u_ex_asset_request | L3: EXAMPLE Laptop Request | M3: All employees; EX Asset Fulfillment | N3: High | O3: Partially Documented | P3: Medium | R3: Basic User | T3: EXAMPLE - FICTIONAL. Not part of your environment. Delete when you no longer need it.

Sheet Tables
A1: TABLES / DATA MODEL - one row per table. Tip: for each table, ask 'who writes it, who reads it, what fires when a row changes, who can see it?'
A2: Table ID | B2: Table Name | C2: Label | D2: Application | E2: Scope | F2: Extends (Parent Table) | G2: Child Tables | H2: Purpose | I2: Business Process | J2: Business Owner | K2: Technical Owner | L2: Primary Key | M2: Display Field | N2: Record Volume | O2: Retention / Archive | P2: Important Fields | Q2: Sensitive Data | R2: Data Source | S2: Tables This References | T2: Tables Referencing This | U2: Many-to-Many Relationships | V2: Dependency Notes | W2: Business Rules | X2: Flows | Y2: Client Scripts | Z2: UI Policies | AA2: Script Includes | AB2: Scheduled Processes | AC2: Other Automation | AD2: Read ACLs | AE2: Create ACLs | AF2: Write ACLs | AG2: Delete ACLs | AH2: Roles | AI2: Groups | AJ2: Sensitive-Data Restrictions | AK2: Written To By (systems) | AL2: Read By (systems) | AM2: APIs | AN2: Import Sets | AO2: Transform Maps | AP2: MID Server Dependencies | AQ2: OOTB/Custom | AR2: Customized OOTB Objects | AS2: Reason for Customization | AT2: Upgrade Implications | AU2: Technical Debt | AV2: Criticality | AW2: Unknowns (link IDs) | AX2: Open Questions | AY2: Documentation Status | AZ2: Confidence | BA2: Evidence / Source | BB2: Access Needed | BC2: Last Reviewed | BD2: Notes
A3: EX-TBL-001 | B3: u_ex_asset_request | C3: Asset Request | D3: EXAMPLE Asset Requests | E3: x_ex_assetreq | F3: task | H3: One row per asset request | I3: EXAMPLE Laptop Request | L3: sys_id | M3: number | N3: ~400/month (fictional) | P3: u_cost_center; u_asset_type; state | Q3: None identified | R3: Catalog + flow | S3: sys_user; cmn_cost_center | W3: EX Set Cost Center Default | X3: EX Laptop Request Fulfillment | AF3: EX ACL write u_ex_asset_request | AH3: x_ex_assetreq.fulfiller | AQ3: Custom | AV3: Critical | AW3: EX-U-001 | AY3: Documented | AZ3: High | BA3: Fictional | BB3: Admin | BD3: EXAMPLE - FICTIONAL. Not part of your environment. Delete when you no longer need it.

Sheet Fields
A1: FIELDS - document only fields that matter: referenced by automation, ACLs, reports, integrations, or that you had to ask about. Column T is the point: what happens downstream when this value changes?
A2: Field ID | B2: Table | C2: Field Name (element) | D2: Label | E2: Type | F2: Length | G2: Reference Table | H2: Reference Qualifier | I2: Default Value | J2: Mandatory | K2: Read-only | L2: Choice Field | M2: Choices | N2: Calculated | O2: Attributes | P2: Dictionary Overrides | Q2: Business Purpose | R2: Read By (rules/flows/reports) | S2: Written By (rules/flows/integrations) | T2: Downstream Behavior (what changes when the value changes) | U2: Dependencies | V2: Criticality | W2: Documentation Status | X2: Confidence | Y2: Evidence / Source | Z2: Access Needed | AA2: Last Reviewed | AB2: Notes
A3: EX-FLD-001 | B3: u_ex_asset_request | C3: u_cost_center | D3: Cost Center | E3: Reference | G3: cmn_cost_center | H3: active=true | J3: Yes | Q3: Charges the asset to a department | R3: Fulfillment flow; Finance report | S3: EX Set Cost Center Default; requester | T3: Selects approver group in flow; changes Finance report grouping | V3: High | W3: Documented | X3: Medium | Z3: Admin | AB3: EXAMPLE - FICTIONAL. Not part of your environment. Delete when you no longer need it.

Sheet Catalog Items
A1: SERVICE CATALOG ITEMS - trace one item end-to-end: what the requester sees -> what records/approvals/tasks/notifications it creates.
A2: Catalog Item ID | B2: Catalog | C2: Category | D2: Name | E2: Technical Name | F2: Business Owner | G2: Technical Owner | H2: Purpose | I2: Business Process | J2: Active | K2: Criticality | L2: Available To (user criteria / roles) | M2: Variables | N2: Variable Sets | O2: UI Policies | P2: Catalog Client Scripts | Q2: Reference Qualifiers | R2: Flow | S2: Subflows | T2: Approvals | U2: Tasks | V2: Notifications | W2: Tables Touched | X2: Integrations | Y2: Users / Groups (requesters, fulfillers) | Z2: Dependencies | AA2: Known Issues | AB2: Documentation Status | AC2: Confidence | AD2: Evidence / Source | AE2: Access Needed | AF2: Last Reviewed | AG2: Notes
A3: EX-CI-001 | B3: Employee Services | C3: Hardware | D3: EXAMPLE Laptop Request | E3: ex_laptop_request | H3: Request a laptop | I3: EXAMPLE Laptop Request | J3: Active | K3: High | L3: All employees | M3: laptop_model; cost_center; justification | R3: EX Laptop Request Fulfillment | S3: EX Get Manager Approval | T3: Manager | U3: Fulfillment task -> EX Asset Fulfillment | V3: Approval request; Shipped | W3: sc_request; sc_req_item; u_ex_asset_request | X3: EX HR Employee Lookup | AB3: Partially Documented | AC3: Medium | AE3: Basic User | AG3: EXAMPLE - FICTIONAL. Not part of your environment. Delete when you no longer need it.

Sheet Variables
A1: VARIABLES - one row per variable that drives behavior (approvals, routing, integrations). Skip purely cosmetic ones.
A2: Variable ID | B2: Variable Name | C2: Label | D2: Type | E2: Catalog Item | F2: Variable Set | G2: Reference Table | H2: Reference Qualifier | I2: Default | J2: Mandatory | K2: Read-only | L2: Visibility Conditions | M2: Catalog Client Scripts | N2: UI Policies | O2: Feeds Into (flow/script/task field that reads it) | P2: Dependencies | Q2: Criticality | R2: Documentation Status | S2: Confidence | T2: Evidence / Source | U2: Access Needed | V2: Last Reviewed | W2: Notes
A3: EX-VAR-001 | B3: laptop_model | C3: Laptop Model | D3: Select Box | E3: EXAMPLE Laptop Request | J3: Yes | O3: Flow branches on model to pick approver; sets u_asset_type | Q3: High | R3: Documented | S3: Medium | U3: Basic User | W3: EXAMPLE - FICTIONAL. Not part of your environment. Delete when you no longer need it.

Sheet Flows
A1: FLOWS / AUTOMATION - the 2 questions: (1) if this flow stops, what breaks? (col AE) (2) if I change table/field X, which flows are affected? (filter 'Tables Read/Updated').
A2: Flow ID | B2: Flow Name | C2: Technical Name | D2: Component Type | E2: Application | F2: Scope | G2: Active | H2: Business Owner | I2: Technical Owner | J2: Purpose | K2: Business Process | L2: Trigger | M2: Trigger Conditions | N2: Inputs | O2: Outputs | P2: Tables Read | Q2: Tables Created | R2: Tables Updated | S2: Subflows Called | T2: Actions Used | U2: Script Actions | V2: Integrations | W2: Notifications | X2: Approvals | Y2: Error Handling | Z2: Failure Behavior | AA2: Logging | AB2: Retry Behavior | AC2: Dependencies | AD2: Dependents | AE2: If This Stops, What Business Process Breaks? | AF2: Criticality | AG2: Known Issues | AH2: Technical Debt | AI2: Documentation Status | AJ2: Confidence | AK2: Evidence / Source | AL2: Access Needed | AM2: Last Reviewed | AN2: Notes
A3: EX-FLOW-001 | B3: EX Laptop Request Fulfillment | C3: x_ex_assetreq.laptop_fulfillment | D3: Flow | E3: EXAMPLE Asset Requests | F3: x_ex_assetreq | G3: Active | J3: Orchestrates approval, task, and record updates | K3: EXAMPLE Laptop Request | L3: Service Catalog (request item created) | M3: Catalog item = EX Laptop Request | P3: sc_req_item; sys_user | Q3: u_ex_asset_request; sc_task | R3: u_ex_asset_request; sc_req_item | S3: EX Get Manager Approval | V3: EX HR Employee Lookup | X3: Manager | Y3: None observed (example) | Z3: UNKNOWN | AA3: Flow execution only | AB3: None | AE3: No laptop requests get approved or fulfilled; requests sit in 'Open' | AF3: Critical | AG3: No alerting on failed executions (example) | AI3: Partially Documented | AJ3: Medium | AL3: Admin | AN3: EXAMPLE - FICTIONAL. Not part of your environment. Delete when you no longer need it.

Sheet Scripts & Rules
A1: SCRIPTS & RULES - Business Rules, Client Scripts, Script Includes, UI Actions, etc. Hunt for hidden dependencies: hard-coded sys_ids, group/user names, other tables written, calls to other scripts (col S).
A2: Script ID | B2: Name | C2: Script Type | D2: Technical Name | E2: Application | F2: Scope | G2: Table | H2: Active | I2: Trigger / When It Runs | J2: Order | K2: Conditions | L2: Purpose (verified, or write UNKNOWN) | M2: Reads | N2: Writes | O2: Functions / Script Includes Called | P2: Called By | Q2: Tables Affected | R2: Other Dependencies | S2: Hard-coded Values (sys_ids, names, emails, URLs) | T2: Potential Side Effects | U2: Performance Concerns | V2: Security Concerns | W2: Criticality | X2: OOTB/Custom | Y2: Known Issues | Z2: Technical Debt | AA2: Documentation Status | AB2: Confidence | AC2: Evidence / Source | AD2: Access Needed | AE2: Last Reviewed | AF2: Notes
A3: EX-SCR-001 | B3: EX Set Cost Center Default | C3: Business Rule | E3: EXAMPLE Asset Requests | F3: x_ex_assetreq | G3: u_ex_asset_request | H3: Active | I3: Before insert | J3: 100 | K3: cost center is empty | L3: UNKNOWN - appears to default cost center; reason not verified | M3: sys_user.department | N3: u_ex_asset_request.u_cost_center | O3: EXCostCenterUtil.getDefault() | Q3: u_ex_asset_request | S3: One hard-coded group sys_id in line 14 (example) | T3: Overrides requester choice if department blank | W3: Medium | X3: Custom | Z3: Hard-coded sys_id | AA3: Discovered | AB3: Low | AD3: Admin | AF3: EXAMPLE - FICTIONAL. Not part of your environment. Delete when you no longer need it.

Sheet Integrations
A1: INTEGRATIONS - every connection in or out. An integration with no known owner, credential expiry or alerting is a risk row waiting to be written.
A2: Integration ID | B2: Integration Name | C2: External System | D2: Direction | E2: Purpose | F2: Technology | G2: API / Service Used | H2: Endpoint / Connection | I2: Authentication | J2: Integration User | K2: Credential Owner / Expiry | L2: MID Server | M2: Data Source | N2: Import Set | O2: Transform Map | P2: Target Table | Q2: Schedule | R2: Trigger | S2: Data Exchanged | T2: Failure Logging | U2: Alerting | V2: Retry / Recovery | W2: Dependencies | X2: Business Owner | Y2: Technical Owner | Z2: External Contact | AA2: Active | AB2: Criticality | AC2: Known Issues | AD2: Documentation Status | AE2: Confidence | AF2: Evidence / Source | AG2: Access Needed | AH2: Last Reviewed | AI2: Notes
A3: EX-INT-001 | B3: EX HR Employee Lookup | C3: EXAMPLE HR System (fictional) | D3: Outbound | E3: Fetch employee manager/cost center | F3: REST | H3: https://hr.example.invalid/api (fictional) | I3: OAuth 2.0 | J3: UNKNOWN | K3: UNKNOWN | R3: Called from fulfillment flow | S3: employee id -> manager, cost center | T3: Unknown | U3: None known | AA3: Active | AB3: High | AD3: Partially Documented | AE3: Low | AG3: Admin | AI3: EXAMPLE - FICTIONAL. Not part of your environment. Delete when you no longer need it.

Sheet Security
A1: SECURITY - roles, groups and ACLs in one table (filter by Record Type). Answers: who can SEE it, CHANGE it, EXECUTE it, and what happens if a role/group/ACL changes?
A2: Security ID | B2: Record Type | C2: Name (role / group / ACL name) | D2: Purpose | E2: Table (ACL) | F2: Field (ACL) | G2: Operation (ACL) | H2: ACL Condition | I2: ACL Script | J2: Required Roles / Parent Roles / Group Roles | K2: Assigned Users / Members (counts or names) | L2: Assigned Groups | M2: Apps / Modules Affected | N2: Privileges / Effect (who can see/change/execute) | O2: Manager / Owner | P2: Business Function | Q2: Responsibilities | R2: Dependencies | S2: What Happens If This Changes? | T2: Security Risk | U2: Active | V2: Criticality | W2: Documentation Status | X2: Confidence | Y2: Evidence / Source | Z2: Access Needed | AA2: Last Reviewed | AB2: Notes
A3: EX-SEC-001 | B3: Role | C3: x_ex_assetreq.fulfiller | D3: Work asset requests | J3: Contains: (none) | L3: EX Asset Fulfillment | M3: EXAMPLE Asset Requests | N3: Read/write u_ex_asset_request | S3: Fulfillers lose access to request records | V3: Medium | W3: Documented | X3: Medium | Z3: Admin | AB3: EXAMPLE - FICTIONAL. Not part of your environment. Delete when you no longer need it.
A4: EX-SEC-002 | B4: ACL | C4: EX ACL write u_ex_asset_request | E4: u_ex_asset_request | F4: * | G4: write | J4: x_ex_assetreq.fulfiller | N4: Only fulfillers can edit | S4: Widening it lets requesters edit approved requests | V4: High | W4: Documented | X4: Medium | Z4: Admin | AB4: EXAMPLE - FICTIONAL. Not part of your environment. Delete when you no longer need it.

Sheet Business Processes
A1: BUSINESS PROCESSES - the spine of this system. Pick 3-5, trace each end-to-end, then link every object you meet back to its process.
A2: Process ID | B2: Process Name | C2: Business Purpose | D2: Process Owner | E2: Trigger | F2: Users Involved | G2: Process Steps (numbered) | H2: ServiceNow Application(s) | I2: Tables | J2: Key Fields | K2: Catalog Items | L2: Flows | M2: Scripts | N2: Notifications | O2: Approvals | P2: Integrations | Q2: Reports | R2: Roles / Groups | S2: Manual Steps | T2: Failure Points | U2: Workarounds | V2: Known Pain Points | W2: Business Impact If It Fails | X2: Volume / Frequency | Y2: Criticality | Z2: Priority to Trace | AA2: SME Validated By | AB2: SME Validated Date | AC2: Documentation Status | AD2: Confidence | AE2: Evidence / Source | AF2: Access Needed | AG2: Last Reviewed | AH2: Notes
A3: EX-BP-001 | B3: EXAMPLE Laptop Request | C3: Employees get approved equipment quickly | D3: (example) IT Operations Manager | E3: Employee submits catalog item | F3: Employee; Manager; Fulfiller | G3: 1 Employee submits. 2 Manager approves. 3 Fulfillment task created. 4 Fulfiller ships. 5 Asset record updated. | H3: EXAMPLE Asset Requests | I3: sc_req_item; u_ex_asset_request | K3: EX Laptop Request | L3: EX Laptop Request Fulfillment | M3: EX Set Cost Center Default | O3: Manager | P3: EX HR Employee Lookup | S3: Shipping handled outside ServiceNow | T3: HR lookup fails -> flow stalls (no alert) | W3: New hires without equipment | Y3: High | Z3: High | AC3: Partially Documented | AD3: Medium | AF3: Basic User | AH3: EXAMPLE - FICTIONAL. Not part of your environment. Delete when you no longer need it.

Sheet Dependencies
A1: DEPENDENCIES - one row = 'Source --relationship--> Target'. Use the SAME names as Object Inventory so Impact Check can find them. Add the reverse reading for free: anything pointing AT an object is a dependent.
A2: Dependency ID | B2: Source Object ID | C2: Source Type | D2: Source Name | E2: Relationship | F2: Target Object ID | G2: Target Type | H2: Target Name | I2: Dependency Type | J2: Criticality | K2: Evidence | L2: Confidence | M2: Date Recorded | N2: Last Verified | O2: Notes | P2: Helper: Inbound # (do not edit) | Q2: Helper: Outbound # (do not edit)
A3: EX-DEP-001 | C3: Catalog Item | D3: EX Laptop Request | E3: launches | G3: Flow | H3: EX Laptop Request Fulfillment | I3: Automation | J3: High | K3: Fictional | L3: Medium | O3: EXAMPLE - FICTIONAL. Not part of your environment. Delete when you no longer need it. | P3: =IF(H3="","",IF(H3='Impact Check'!$B$3,COUNTIF($H$3:H3,'Impact Check'!$B$3),"")) | Q3: =IF(D3="","",IF(D3='Impact Check'!$B$3,COUNTIF($D$3:D3,'Impact Check'!$B$3),""))
A4: EX-DEP-002 | C4: Flow | D4: EX Laptop Request Fulfillment | E4: calls | G4: Subflow | H4: EX Get Manager Approval | I4: Automation | J4: High | K4: Fictional | L4: Medium | O4: EXAMPLE - FICTIONAL. Not part of your environment. Delete when you no longer need it. | P4: =IF(H4="","",IF(H4='Impact Check'!$B$3,COUNTIF($H$3:H4,'Impact Check'!$B$3),"")) | Q4: =IF(D4="","",IF(D4='Impact Check'!$B$3,COUNTIF($D$3:D4,'Impact Check'!$B$3),""))
A5: EX-DEP-003 | C5: Flow | D5: EX Laptop Request Fulfillment | E5: updates | G5: Table | H5: u_ex_asset_request | I5: Data | J5: Critical | K5: Fictional | L5: Medium | O5: EXAMPLE - FICTIONAL. Not part of your environment. Delete when you no longer need it. | P5: =IF(H5="","",IF(H5='Impact Check'!$B$3,COUNTIF($H$3:H5,'Impact Check'!$B$3),"")) -> 1 | Q5: =IF(D5="","",IF(D5='Impact Check'!$B$3,COUNTIF($D$3:D5,'Impact Check'!$B$3),""))
A6: EX-DEP-004 | C6: Flow | D6: EX Laptop Request Fulfillment | E6: calls | G6: Integration | H6: EX HR Employee Lookup | I6: Integration | J6: High | K6: Fictional | L6: Low | O6: EXAMPLE - FICTIONAL. Not part of your environment. Delete when you no longer need it. | P6: =IF(H6="","",IF(H6='Impact Check'!$B$3,COUNTIF($H$3:H6,'Impact Check'!$B$3),"")) | Q6: =IF(D6="","",IF(D6='Impact Check'!$B$3,COUNTIF($D$3:D6,'Impact Check'!$B$3),""))
A7: EX-DEP-005 | C7: Business Rule | D7: EX Set Cost Center Default | E7: runs on | G7: Table | H7: u_ex_asset_request | I7: Code | J7: Medium | K7: Fictional | L7: Medium | O7: EXAMPLE - FICTIONAL. Not part of your environment. Delete when you no longer need it. | P7: =IF(H7="","",IF(H7='Impact Check'!$B$3,COUNTIF($H$3:H7,'Impact Check'!$B$3),"")) -> 2 | Q7: =IF(D7="","",IF(D7='Impact Check'!$B$3,COUNTIF($D$3:D7,'Impact Check'!$B$3),""))
A8: EX-DEP-006 | C8: Business Rule | D8: EX Set Cost Center Default | E8: calls | G8: Script Include | H8: EXCostCenterUtil | I8: Code | J8: Medium | K8: Fictional | L8: Medium | O8: EXAMPLE - FICTIONAL. Not part of your environment. Delete when you no longer need it. | P8: =IF(H8="","",IF(H8='Impact Check'!$B$3,COUNTIF($H$3:H8,'Impact Check'!$B$3),"")) | Q8: =IF(D8="","",IF(D8='Impact Check'!$B$3,COUNTIF($D$3:D8,'Impact Check'!$B$3),""))
A9: EX-DEP-007 | C9: ACL | D9: EX ACL write u_ex_asset_request | E9: protects | G9: Table | H9: u_ex_asset_request | I9: Security | J9: High | K9: Fictional | L9: Medium | O9: EXAMPLE - FICTIONAL. Not part of your environment. Delete when you no longer need it. | P9: =IF(H9="","",IF(H9='Impact Check'!$B$3,COUNTIF($H$3:H9,'Impact Check'!$B$3),"")) -> 3 | Q9: =IF(D9="","",IF(D9='Impact Check'!$B$3,COUNTIF($D$3:D9,'Impact Check'!$B$3),""))
A10: EX-DEP-008 | C10: ACL | D10: EX ACL write u_ex_asset_request | E10: requires role | G10: Role | H10: x_ex_assetreq.fulfiller | I10: Security | J10: High | K10: Fictional | L10: Medium | O10: EXAMPLE - FICTIONAL. Not part of your environment. Delete when you no longer need it. | P10: =IF(H10="","",IF(H10='Impact Check'!$B$3,COUNTIF($H$3:H10,'Impact Check'!$B$3),"")) | Q10: =IF(D10="","",IF(D10='Impact Check'!$B$3,COUNTIF($D$3:D10,'Impact Check'!$B$3),""))
A11: EX-DEP-009 | C11: Report | D11: EX Asset Requests Report | E11: reports on | G11: Table | H11: u_ex_asset_request | I11: Reporting | J11: Low | K11: Fictional | L11: Low | O11: EXAMPLE - FICTIONAL. Not part of your environment. Delete when you no longer need it. | P11: =IF(H11="","",IF(H11='Impact Check'!$B$3,COUNTIF($H$3:H11,'Impact Check'!$B$3),"")) -> 4 | Q11: =IF(D11="","",IF(D11='Impact Check'!$B$3,COUNTIF($D$3:D11,'Impact Check'!$B$3),""))
P12: =IF(H12="","",IF(H12='Impact Check'!$B$3,COUNTIF($H$3:H12,'Impact Check'!$B$3),"")) | Q12: =IF(D12="","",IF(D12='Impact Check'!$B$3,COUNTIF($D$3:D12,'Impact Check'!$B$3),""))
P13: =IF(H13="","",IF(H13='Impact Check'!$B$3,COUNTIF($H$3:H13,'Impact Check'!$B$3),"")) | Q13: =IF(D13="","",IF(D13='Impact Check'!$B$3,COUNTIF($D$3:D13,'Impact Check'!$B$3),""))
P14: =IF(H14="","",IF(H14='Impact Check'!$B$3,COUNTIF($H$3:H14,'Impact Check'!$B$3),"")) | Q14: =IF(D14="","",IF(D14='Impact Check'!$B$3,COUNTIF($D$3:D14,'Impact Check'!$B$3),""))
P15: =IF(H15="","",IF(H15='Impact Check'!$B$3,COUNTIF($H$3:H15,'Impact Check'!$B$3),"")) | Q15: =IF(D15="","",IF(D15='Impact Check'!$B$3,COUNTIF($D$3:D15,'Impact Check'!$B$3),""))
P16: =IF(H16="","",IF(H16='Impact Check'!$B$3,COUNTIF($H$3:H16,'Impact Check'!$B$3),"")) | Q16: =IF(D16="","",IF(D16='Impact Check'!$B$3,COUNTIF($D$3:D16,'Impact Check'!$B$3),""))
P17: =IF(H17="","",IF(H17='Impact Check'!$B$3,COUNTIF($H$3:H17,'Impact Check'!$B$3),"")) | Q17: =IF(D17="","",IF(D17='Impact Check'!$B$3,COUNTIF($D$3:D17,'Impact Check'!$B$3),""))
P18: =IF(H18="","",IF(H18='Impact Check'!$B$3,COUNTIF($H$3:H18,'Impact Check'!$B$3),"")) | Q18: =IF(D18="","",IF(D18='Impact Check'!$B$3,COUNTIF($D$3:D18,'Impact Check'!$B$3),""))
P19: =IF(H19="","",IF(H19='Impact Check'!$B$3,COUNTIF($H$3:H19,'Impact Check'!$B$3),"")) | Q19: =IF(D19="","",IF(D19='Impact Check'!$B$3,COUNTIF($D$3:D19,'Impact Check'!$B$3),""))
P20: =IF(H20="","",IF(H20='Impact Check'!$B$3,COUNTIF($H$3:H20,'Impact Check'!$B$3),"")) | Q20: =IF(D20="","",IF(D20='Impact Check'!$B$3,COUNTIF($D$3:D20,'Impact Check'!$B$3),""))
P21: =IF(H21="","",IF(H21='Impact Check'!$B$3,COUNTIF($H$3:H21,'Impact Check'!$B$3),"")) | Q21: =IF(D21="","",IF(D21='Impact Check'!$B$3,COUNTIF($D$3:D21,'Impact Check'!$B$3),""))
P22: =IF(H22="","",IF(H22='Impact Check'!$B$3,COUNTIF($H$3:H22,'Impact Check'!$B$3),"")) | Q22: =IF(D22="","",IF(D22='Impact Check'!$B$3,COUNTIF($D$3:D22,'Impact Check'!$B$3),""))
P23: =IF(H23="","",IF(H23='Impact Check'!$B$3,COUNTIF($H$3:H23,'Impact Check'!$B$3),"")) | Q23: =IF(D23="","",IF(D23='Impact Check'!$B$3,COUNTIF($D$3:D23,'Impact Check'!$B$3),""))
... P502: =IF(H502="","",IF(H502='Impact Check'!$B$3,COUNTIF($H$3:H502,'Impact Check'!$B$3),"")) | Q502: =IF(D502="","",IF(D502='Impact Check'!$B$3,COUNTIF($D$3:D502,'Impact Check'!$B$3),""))

Sheet Impact Check
A1: IMPACT CHECK - 'If I change this, what could break?'
A3: Object name (exact match to Dependencies sheet): | B3: u_ex_asset_request | C3: <- type an object name (example value is fictional). Then repeat for each dependent you find: that is your second-hop impact.
A5: Rows that point AT this object (dependents): | B5: =COUNTIF(Dependencies!$H$3:$H$502,B3) -> 4
A6: Rows this object points TO (it relies on): | B6: =COUNTIF(Dependencies!$D$3:$D$502,B3) -> 0
A7: Confidence warning: | B7: =IF(B5+B6=0,"Nothing recorded. That means 'not documented', NOT 'no dependencies'. Log an Unknown.",IF(COUNTIFS(Dependencies!$H$3:$H$502,B3,Dependencies!$L$3:$L$502,"Low")+COUNTIFS(Dependencies!$D$3:$D$502,B3,Dependencies!$L$3:$L$502,"Low")>0,"Some links are Low confidence - verify before relying on this list.","OK")) -> Some links are Low confidence - verify before relying on this list.
A9: IF I CHANGE THIS, THESE COULD BREAK (dependents)
A10: # | B10: Dependent (source object) | C10: Relationship | D10: Other Object Type | E10: Dependency Type | F10: Criticality | G10: Confidence | H10: Evidence
A11: 1 | B11: =IFERROR(INDEX(Dependencies!$D$3:$D$502,MATCH($A11,Dependencies!$P$3:$P$502,0)),"") -> EX Laptop Request Fulfillment | C11: =IFERROR(INDEX(Dependencies!$E$3:$E$502,MATCH($A11,Dependencies!$P$3:$P$502,0)),"") -> updates | D11: =IFERROR(INDEX(Dependencies!$C$3:$C$502,MATCH($A11,Dependencies!$P$3:$P$502,0)),"") -> Flow | E11: =IFERROR(INDEX(Dependencies!$I$3:$I$502,MATCH($A11,Dependencies!$P$3:$P$502,0)),"") -> Data | F11: =IFERROR(INDEX(Dependencies!$J$3:$J$502,MATCH($A11,Dependencies!$P$3:$P$502,0)),"") -> Critical | G11: =IFERROR(INDEX(Dependencies!$L$3:$L$502,MATCH($A11,Dependencies!$P$3:$P$502,0)),"") -> Medium | H11: =IFERROR(INDEX(Dependencies!$K$3:$K$502,MATCH($A11,Dependencies!$P$3:$P$502,0)),"") -> Fictional
A12: 2 | B12: =IFERROR(INDEX(Dependencies!$D$3:$D$502,MATCH($A12,Dependencies!$P$3:$P$502,0)),"") -> EX Set Cost Center Default | C12: =IFERROR(INDEX(Dependencies!$E$3:$E$502,MATCH($A12,Dependencies!$P$3:$P$502,0)),"") -> runs on | D12: =IFERROR(INDEX(Dependencies!$C$3:$C$502,MATCH($A12,Dependencies!$P$3:$P$502,0)),"") -> Business Rule | E12: =IFERROR(INDEX(Dependencies!$I$3:$I$502,MATCH($A12,Dependencies!$P$3:$P$502,0)),"") -> Code | F12: =IFERROR(INDEX(Dependencies!$J$3:$J$502,MATCH($A12,Dependencies!$P$3:$P$502,0)),"") -> Medium | G12: =IFERROR(INDEX(Dependencies!$L$3:$L$502,MATCH($A12,Dependencies!$P$3:$P$502,0)),"") -> Medium | H12: =IFERROR(INDEX(Dependencies!$K$3:$K$502,MATCH($A12,Dependencies!$P$3:$P$502,0)),"") -> Fictional
A13: 3 | B13: =IFERROR(INDEX(Dependencies!$D$3:$D$502,MATCH($A13,Dependencies!$P$3:$P$502,0)),"") -> EX ACL write u_ex_asset_request | C13: =IFERROR(INDEX(Dependencies!$E$3:$E$502,MATCH($A13,Dependencies!$P$3:$P$502,0)),"") -> protects | D13: =IFERROR(INDEX(Dependencies!$C$3:$C$502,MATCH($A13,Dependencies!$P$3:$P$502,0)),"") -> ACL | E13: =IFERROR(INDEX(Dependencies!$I$3:$I$502,MATCH($A13,Dependencies!$P$3:$P$502,0)),"") -> Security | F13: =IFERROR(INDEX(Dependencies!$J$3:$J$502,MATCH($A13,Dependencies!$P$3:$P$502,0)),"") -> High | G13: =IFERROR(INDEX(Dependencies!$L$3:$L$502,MATCH($A13,Dependencies!$P$3:$P$502,0)),"") -> Medium | H13: =IFERROR(INDEX(Dependencies!$K$3:$K$502,MATCH($A13,Dependencies!$P$3:$P$502,0)),"") -> Fictional
A14: 4 | B14: =IFERROR(INDEX(Dependencies!$D$3:$D$502,MATCH($A14,Dependencies!$P$3:$P$502,0)),"") -> EX Asset Requests Report | C14: =IFERROR(INDEX(Dependencies!$E$3:$E$502,MATCH($A14,Dependencies!$P$3:$P$502,0)),"") -> reports on | D14: =IFERROR(INDEX(Dependencies!$C$3:$C$502,MATCH($A14,Dependencies!$P$3:$P$502,0)),"") -> Report | E14: =IFERROR(INDEX(Dependencies!$I$3:$I$502,MATCH($A14,Dependencies!$P$3:$P$502,0)),"") -> Reporting | F14: =IFERROR(INDEX(Dependencies!$J$3:$J$502,MATCH($A14,Dependencies!$P$3:$P$502,0)),"") -> Low | G14: =IFERROR(INDEX(Dependencies!$L$3:$L$502,MATCH($A14,Dependencies!$P$3:$P$502,0)),"") -> Low | H14: =IFERROR(INDEX(Dependencies!$K$3:$K$502,MATCH($A14,Dependencies!$P$3:$P$502,0)),"") -> Fictional
A15: 5 | B15: =IFERROR(INDEX(Dependencies!$D$3:$D$502,MATCH($A15,Dependencies!$P$3:$P$502,0)),"") | C15: =IFERROR(INDEX(Dependencies!$E$3:$E$502,MATCH($A15,Dependencies!$P$3:$P$502,0)),"") | D15: =IFERROR(INDEX(Dependencies!$C$3:$C$502,MATCH($A15,Dependencies!$P$3:$P$502,0)),"") | E15: =IFERROR(INDEX(Dependencies!$I$3:$I$502,MATCH($A15,Dependencies!$P$3:$P$502,0)),"") | F15: =IFERROR(INDEX(Dependencies!$J$3:$J$502,MATCH($A15,Dependencies!$P$3:$P$502,0)),"") | G15: =IFERROR(INDEX(Dependencies!$L$3:$L$502,MATCH($A15,Dependencies!$P$3:$P$502,0)),"") | H15: =IFERROR(INDEX(Dependencies!$K$3:$K$502,MATCH($A15,Dependencies!$P$3:$P$502,0)),"")
A16: 6 | B16: =IFERROR(INDEX(Dependencies!$D$3:$D$502,MATCH($A16,Dependencies!$P$3:$P$502,0)),"") | C16: =IFERROR(INDEX(Dependencies!$E$3:$E$502,MATCH($A16,Dependencies!$P$3:$P$502,0)),"") | D16: =IFERROR(INDEX(Dependencies!$C$3:$C$502,MATCH($A16,Dependencies!$P$3:$P$502,0)),"") | E16: =IFERROR(INDEX(Dependencies!$I$3:$I$502,MATCH($A16,Dependencies!$P$3:$P$502,0)),"") | F16: =IFERROR(INDEX(Dependencies!$J$3:$J$502,MATCH($A16,Dependencies!$P$3:$P$502,0)),"") | G16: =IFERROR(INDEX(Dependencies!$L$3:$L$502,MATCH($A16,Dependencies!$P$3:$P$502,0)),"") | H16: =IFERROR(INDEX(Dependencies!$K$3:$K$502,MATCH($A16,Dependencies!$P$3:$P$502,0)),"")
A17: 7 | B17: =IFERROR(INDEX(Dependencies!$D$3:$D$502,MATCH($A17,Dependencies!$P$3:$P$502,0)),"") | C17: =IFERROR(INDEX(Dependencies!$E$3:$E$502,MATCH($A17,Dependencies!$P$3:$P$502,0)),"") | D17: =IFERROR(INDEX(Dependencies!$C$3:$C$502,MATCH($A17,Dependencies!$P$3:$P$502,0)),"") | E17: =IFERROR(INDEX(Dependencies!$I$3:$I$502,MATCH($A17,Dependencies!$P$3:$P$502,0)),"") | F17: =IFERROR(INDEX(Dependencies!$J$3:$J$502,MATCH($A17,Dependencies!$P$3:$P$502,0)),"") | G17: =IFERROR(INDEX(Dependencies!$L$3:$L$502,MATCH($A17,Dependencies!$P$3:$P$502,0)),"") | H17: =IFERROR(INDEX(Dependencies!$K$3:$K$502,MATCH($A17,Dependencies!$P$3:$P$502,0)),"")
A18: 8 | B18: =IFERROR(INDEX(Dependencies!$D$3:$D$502,MATCH($A18,Dependencies!$P$3:$P$502,0)),"") | C18: =IFERROR(INDEX(Dependencies!$E$3:$E$502,MATCH($A18,Dependencies!$P$3:$P$502,0)),"") | D18: =IFERROR(INDEX(Dependencies!$C$3:$C$502,MATCH($A18,Dependencies!$P$3:$P$502,0)),"") | E18: =IFERROR(INDEX(Dependencies!$I$3:$I$502,MATCH($A18,Dependencies!$P$3:$P$502,0)),"") | F18: =IFERROR(INDEX(Dependencies!$J$3:$J$502,MATCH($A18,Dependencies!$P$3:$P$502,0)),"") | G18: =IFERROR(INDEX(Dependencies!$L$3:$L$502,MATCH($A18,Dependencies!$P$3:$P$502,0)),"") | H18: =IFERROR(INDEX(Dependencies!$K$3:$K$502,MATCH($A18,Dependencies!$P$3:$P$502,0)),"")
A19: 9 | B19: =IFERROR(INDEX(Dependencies!$D$3:$D$502,MATCH($A19,Dependencies!$P$3:$P$502,0)),"") | C19: =IFERROR(INDEX(Dependencies!$E$3:$E$502,MATCH($A19,Dependencies!$P$3:$P$502,0)),"") | D19: =IFERROR(INDEX(Dependencies!$C$3:$C$502,MATCH($A19,Dependencies!$P$3:$P$502,0)),"") | E19: =IFERROR(INDEX(Dependencies!$I$3:$I$502,MATCH($A19,Dependencies!$P$3:$P$502,0)),"") | F19: =IFERROR(INDEX(Dependencies!$J$3:$J$502,MATCH($A19,Dependencies!$P$3:$P$502,0)),"") | G19: =IFERROR(INDEX(Dependencies!$L$3:$L$502,MATCH($A19,Dependencies!$P$3:$P$502,0)),"") | H19: =IFERROR(INDEX(Dependencies!$K$3:$K$502,MATCH($A19,Dependencies!$P$3:$P$502,0)),"")
A20: 10 | B20: =IFERROR(INDEX(Dependencies!$D$3:$D$502,MATCH($A20,Dependencies!$P$3:$P$502,0)),"") | C20: =IFERROR(INDEX(Dependencies!$E$3:$E$502,MATCH($A20,Dependencies!$P$3:$P$502,0)),"") | D20: =IFERROR(INDEX(Dependencies!$C$3:$C$502,MATCH($A20,Dependencies!$P$3:$P$502,0)),"") | E20: =IFERROR(INDEX(Dependencies!$I$3:$I$502,MATCH($A20,Dependencies!$P$3:$P$502,0)),"") | F20: =IFERROR(INDEX(Dependencies!$J$3:$J$502,MATCH($A20,Dependencies!$P$3:$P$502,0)),"") | G20: =IFERROR(INDEX(Dependencies!$L$3:$L$502,MATCH($A20,Dependencies!$P$3:$P$502,0)),"") | H20: =IFERROR(INDEX(Dependencies!$K$3:$K$502,MATCH($A20,Dependencies!$P$3:$P$502,0)),"")
A21: 11 | B21: =IFERROR(INDEX(Dependencies!$D$3:$D$502,MATCH($A21,Dependencies!$P$3:$P$502,0)),"") | C21: =IFERROR(INDEX(Dependencies!$E$3:$E$502,MATCH($A21,Dependencies!$P$3:$P$502,0)),"") | D21: =IFERROR(INDEX(Dependencies!$C$3:$C$502,MATCH($A21,Dependencies!$P$3:$P$502,0)),"") | E21: =IFERROR(INDEX(Dependencies!$I$3:$I$502,MATCH($A21,Dependencies!$P$3:$P$502,0)),"") | F21: =IFERROR(INDEX(Dependencies!$J$3:$J$502,MATCH($A21,Dependencies!$P$3:$P$502,0)),"") | G21: =IFERROR(INDEX(Dependencies!$L$3:$L$502,MATCH($A21,Dependencies!$P$3:$P$502,0)),"") | H21: =IFERROR(INDEX(Dependencies!$K$3:$K$502,MATCH($A21,Dependencies!$P$3:$P$502,0)),"")
A22: 12 | B22: =IFERROR(INDEX(Dependencies!$D$3:$D$502,MATCH($A22,Dependencies!$P$3:$P$502,0)),"") | C22: =IFERROR(INDEX(Dependencies!$E$3:$E$502,MATCH($A22,Dependencies!$P$3:$P$502,0)),"") | D22: =IFERROR(INDEX(Dependencies!$C$3:$C$502,MATCH($A22,Dependencies!$P$3:$P$502,0)),"") | E22: =IFERROR(INDEX(Dependencies!$I$3:$I$502,MATCH($A22,Dependencies!$P$3:$P$502,0)),"") | F22: =IFERROR(INDEX(Dependencies!$J$3:$J$502,MATCH($A22,Dependencies!$P$3:$P$502,0)),"") | G22: =IFERROR(INDEX(Dependencies!$L$3:$L$502,MATCH($A22,Dependencies!$P$3:$P$502,0)),"") | H22: =IFERROR(INDEX(Dependencies!$K$3:$K$502,MATCH($A22,Dependencies!$P$3:$P$502,0)),"")
... A35: 25 | B35: =IFERROR(INDEX(Dependencies!$D$3:$D$502,MATCH($A35,Dependencies!$P$3:$P$502,0)),"") | C35: =IFERROR(INDEX(Dependencies!$E$3:$E$502,MATCH($A35,Dependencies!$P$3:$P$502,0)),"") | D35: =IFERROR(INDEX(Dependencies!$C$3:$C$502,MATCH($A35,Dependencies!$P$3:$P$502,0)),"") | E35: =IFERROR(INDEX(Dependencies!$I$3:$I$502,MATCH($A35,Dependencies!$P$3:$P$502,0)),"") | F35: =IFERROR(INDEX(Dependencies!$J$3:$J$502,MATCH($A35,Dependencies!$P$3:$P$502,0)),"") | G35: =IFERROR(INDEX(Dependencies!$L$3:$L$502,MATCH($A35,Dependencies!$P$3:$P$502,0)),"") | H35: =IFERROR(INDEX(Dependencies!$K$3:$K$502,MATCH($A35,Dependencies!$P$3:$P$502,0)),"")
A37: THIS OBJECT RELIES ON (its dependencies)
A38: # | B38: Depends On (target object) | C38: Relationship | D38: Other Object Type | E38: Dependency Type | F38: Criticality | G38: Confidence | H38: Evidence
A39: 1 | B39: =IFERROR(INDEX(Dependencies!$H$3:$H$502,MATCH($A39,Dependencies!$Q$3:$Q$502,0)),"") | C39: =IFERROR(INDEX(Dependencies!$E$3:$E$502,MATCH($A39,Dependencies!$Q$3:$Q$502,0)),"") | D39: =IFERROR(INDEX(Dependencies!$G$3:$G$502,MATCH($A39,Dependencies!$Q$3:$Q$502,0)),"") | E39: =IFERROR(INDEX(Dependencies!$I$3:$I$502,MATCH($A39,Dependencies!$Q$3:$Q$502,0)),"") | F39: =IFERROR(INDEX(Dependencies!$J$3:$J$502,MATCH($A39,Dependencies!$Q$3:$Q$502,0)),"") | G39: =IFERROR(INDEX(Dependencies!$L$3:$L$502,MATCH($A39,Dependencies!$Q$3:$Q$502,0)),"") | H39: =IFERROR(INDEX(Dependencies!$K$3:$K$502,MATCH($A39,Dependencies!$Q$3:$Q$502,0)),"")
A40: 2 | B40: =IFERROR(INDEX(Dependencies!$H$3:$H$502,MATCH($A40,Dependencies!$Q$3:$Q$502,0)),"") | C40: =IFERROR(INDEX(Dependencies!$E$3:$E$502,MATCH($A40,Dependencies!$Q$3:$Q$502,0)),"") | D40: =IFERROR(INDEX(Dependencies!$G$3:$G$502,MATCH($A40,Dependencies!$Q$3:$Q$502,0)),"") | E40: =IFERROR(INDEX(Dependencies!$I$3:$I$502,MATCH($A40,Dependencies!$Q$3:$Q$502,0)),"") | F40: =IFERROR(INDEX(Dependencies!$J$3:$J$502,MATCH($A40,Dependencies!$Q$3:$Q$502,0)),"") | G40: =IFERROR(INDEX(Dependencies!$L$3:$L$502,MATCH($A40,Dependencies!$Q$3:$Q$502,0)),"") | H40: =IFERROR(INDEX(Dependencies!$K$3:$K$502,MATCH($A40,Dependencies!$Q$3:$Q$502,0)),"")
A41: 3 | B41: =IFERROR(INDEX(Dependencies!$H$3:$H$502,MATCH($A41,Dependencies!$Q$3:$Q$502,0)),"") | C41: =IFERROR(INDEX(Dependencies!$E$3:$E$502,MATCH($A41,Dependencies!$Q$3:$Q$502,0)),"") | D41: =IFERROR(INDEX(Dependencies!$G$3:$G$502,MATCH($A41,Dependencies!$Q$3:$Q$502,0)),"") | E41: =IFERROR(INDEX(Dependencies!$I$3:$I$502,MATCH($A41,Dependencies!$Q$3:$Q$502,0)),"") | F41: =IFERROR(INDEX(Dependencies!$J$3:$J$502,MATCH($A41,Dependencies!$Q$3:$Q$502,0)),"") | G41: =IFERROR(INDEX(Dependencies!$L$3:$L$502,MATCH($A41,Dependencies!$Q$3:$Q$502,0)),"") | H41: =IFERROR(INDEX(Dependencies!$K$3:$K$502,MATCH($A41,Dependencies!$Q$3:$Q$502,0)),"")
A42: 4 | B42: =IFERROR(INDEX(Dependencies!$H$3:$H$502,MATCH($A42,Dependencies!$Q$3:$Q$502,0)),"") | C42: =IFERROR(INDEX(Dependencies!$E$3:$E$502,MATCH($A42,Dependencies!$Q$3:$Q$502,0)),"") | D42: =IFERROR(INDEX(Dependencies!$G$3:$G$502,MATCH($A42,Dependencies!$Q$3:$Q$502,0)),"") | E42: =IFERROR(INDEX(Dependencies!$I$3:$I$502,MATCH($A42,Dependencies!$Q$3:$Q$502,0)),"") | F42: =IFERROR(INDEX(Dependencies!$J$3:$J$502,MATCH($A42,Dependencies!$Q$3:$Q$502,0)),"") | G42: =IFERROR(INDEX(Dependencies!$L$3:$L$502,MATCH($A42,Dependencies!$Q$3:$Q$502,0)),"") | H42: =IFERROR(INDEX(Dependencies!$K$3:$K$502,MATCH($A42,Dependencies!$Q$3:$Q$502,0)),"")
A43: 5 | B43: =IFERROR(INDEX(Dependencies!$H$3:$H$502,MATCH($A43,Dependencies!$Q$3:$Q$502,0)),"") | C43: =IFERROR(INDEX(Dependencies!$E$3:$E$502,MATCH($A43,Dependencies!$Q$3:$Q$502,0)),"") | D43: =IFERROR(INDEX(Dependencies!$G$3:$G$502,MATCH($A43,Dependencies!$Q$3:$Q$502,0)),"") | E43: =IFERROR(INDEX(Dependencies!$I$3:$I$502,MATCH($A43,Dependencies!$Q$3:$Q$502,0)),"") | F43: =IFERROR(INDEX(Dependencies!$J$3:$J$502,MATCH($A43,Dependencies!$Q$3:$Q$502,0)),"") | G43: =IFERROR(INDEX(Dependencies!$L$3:$L$502,MATCH($A43,Dependencies!$Q$3:$Q$502,0)),"") | H43: =IFERROR(INDEX(Dependencies!$K$3:$K$502,MATCH($A43,Dependencies!$Q$3:$Q$502,0)),"")
A44: 6 | B44: =IFERROR(INDEX(Dependencies!$H$3:$H$502,MATCH($A44,Dependencies!$Q$3:$Q$502,0)),"") | C44: =IFERROR(INDEX(Dependencies!$E$3:$E$502,MATCH($A44,Dependencies!$Q$3:$Q$502,0)),"") | D44: =IFERROR(INDEX(Dependencies!$G$3:$G$502,MATCH($A44,Dependencies!$Q$3:$Q$502,0)),"") | E44: =IFERROR(INDEX(Dependencies!$I$3:$I$502,MATCH($A44,Dependencies!$Q$3:$Q$502,0)),"") | F44: =IFERROR(INDEX(Dependencies!$J$3:$J$502,MATCH($A44,Dependencies!$Q$3:$Q$502,0)),"") | G44: =IFERROR(INDEX(Dependencies!$L$3:$L$502,MATCH($A44,Dependencies!$Q$3:$Q$502,0)),"") | H44: =IFERROR(INDEX(Dependencies!$K$3:$K$502,MATCH($A44,Dependencies!$Q$3:$Q$502,0)),"")
A45: 7 | B45: =IFERROR(INDEX(Dependencies!$H$3:$H$502,MATCH($A45,Dependencies!$Q$3:$Q$502,0)),"") | C45: =IFERROR(INDEX(Dependencies!$E$3:$E$502,MATCH($A45,Dependencies!$Q$3:$Q$502,0)),"") | D45: =IFERROR(INDEX(Dependencies!$G$3:$G$502,MATCH($A45,Dependencies!$Q$3:$Q$502,0)),"") | E45: =IFERROR(INDEX(Dependencies!$I$3:$I$502,MATCH($A45,Dependencies!$Q$3:$Q$502,0)),"") | F45: =IFERROR(INDEX(Dependencies!$J$3:$J$502,MATCH($A45,Dependencies!$Q$3:$Q$502,0)),"") | G45: =IFERROR(INDEX(Dependencies!$L$3:$L$502,MATCH($A45,Dependencies!$Q$3:$Q$502,0)),"") | H45: =IFERROR(INDEX(Dependencies!$K$3:$K$502,MATCH($A45,Dependencies!$Q$3:$Q$502,0)),"")
A46: 8 | B46: =IFERROR(INDEX(Dependencies!$H$3:$H$502,MATCH($A46,Dependencies!$Q$3:$Q$502,0)),"") | C46: =IFERROR(INDEX(Dependencies!$E$3:$E$502,MATCH($A46,Dependencies!$Q$3:$Q$502,0)),"") | D46: =IFERROR(INDEX(Dependencies!$G$3:$G$502,MATCH($A46,Dependencies!$Q$3:$Q$502,0)),"") | E46: =IFERROR(INDEX(Dependencies!$I$3:$I$502,MATCH($A46,Dependencies!$Q$3:$Q$502,0)),"") | F46: =IFERROR(INDEX(Dependencies!$J$3:$J$502,MATCH($A46,Dependencies!$Q$3:$Q$502,0)),"") | G46: =IFERROR(INDEX(Dependencies!$L$3:$L$502,MATCH($A46,Dependencies!$Q$3:$Q$502,0)),"") | H46: =IFERROR(INDEX(Dependencies!$K$3:$K$502,MATCH($A46,Dependencies!$Q$3:$Q$502,0)),"")
A47: 9 | B47: =IFERROR(INDEX(Dependencies!$H$3:$H$502,MATCH($A47,Dependencies!$Q$3:$Q$502,0)),"") | C47: =IFERROR(INDEX(Dependencies!$E$3:$E$502,MATCH($A47,Dependencies!$Q$3:$Q$502,0)),"") | D47: =IFERROR(INDEX(Dependencies!$G$3:$G$502,MATCH($A47,Dependencies!$Q$3:$Q$502,0)),"") | E47: =IFERROR(INDEX(Dependencies!$I$3:$I$502,MATCH($A47,Dependencies!$Q$3:$Q$502,0)),"") | F47: =IFERROR(INDEX(Dependencies!$J$3:$J$502,MATCH($A47,Dependencies!$Q$3:$Q$502,0)),"") | G47: =IFERROR(INDEX(Dependencies!$L$3:$L$502,MATCH($A47,Dependencies!$Q$3:$Q$502,0)),"") | H47: =IFERROR(INDEX(Dependencies!$K$3:$K$502,MATCH($A47,Dependencies!$Q$3:$Q$502,0)),"")
A48: 10 | B48: =IFERROR(INDEX(Dependencies!$H$3:$H$502,MATCH($A48,Dependencies!$Q$3:$Q$502,0)),"") | C48: =IFERROR(INDEX(Dependencies!$E$3:$E$502,MATCH($A48,Dependencies!$Q$3:$Q$502,0)),"") | D48: =IFERROR(INDEX(Dependencies!$G$3:$G$502,MATCH($A48,Dependencies!$Q$3:$Q$502,0)),"") | E48: =IFERROR(INDEX(Dependencies!$I$3:$I$502,MATCH($A48,Dependencies!$Q$3:$Q$502,0)),"") | F48: =IFERROR(INDEX(Dependencies!$J$3:$J$502,MATCH($A48,Dependencies!$Q$3:$Q$502,0)),"") | G48: =IFERROR(INDEX(Dependencies!$L$3:$L$502,MATCH($A48,Dependencies!$Q$3:$Q$502,0)),"") | H48: =IFERROR(INDEX(Dependencies!$K$3:$K$502,MATCH($A48,Dependencies!$Q$3:$Q$502,0)),"")
A49: 11 | B49: =IFERROR(INDEX(Dependencies!$H$3:$H$502,MATCH($A49,Dependencies!$Q$3:$Q$502,0)),"") | C49: =IFERROR(INDEX(Dependencies!$E$3:$E$502,MATCH($A49,Dependencies!$Q$3:$Q$502,0)),"") | D49: =IFERROR(INDEX(Dependencies!$G$3:$G$502,MATCH($A49,Dependencies!$Q$3:$Q$502,0)),"") | E49: =IFERROR(INDEX(Dependencies!$I$3:$I$502,MATCH($A49,Dependencies!$Q$3:$Q$502,0)),"") | F49: =IFERROR(INDEX(Dependencies!$J$3:$J$502,MATCH($A49,Dependencies!$Q$3:$Q$502,0)),"") | G49: =IFERROR(INDEX(Dependencies!$L$3:$L$502,MATCH($A49,Dependencies!$Q$3:$Q$502,0)),"") | H49: =IFERROR(INDEX(Dependencies!$K$3:$K$502,MATCH($A49,Dependencies!$Q$3:$Q$502,0)),"")
A50: 12 | B50: =IFERROR(INDEX(Dependencies!$H$3:$H$502,MATCH($A50,Dependencies!$Q$3:$Q$502,0)),"") | C50: =IFERROR(INDEX(Dependencies!$E$3:$E$502,MATCH($A50,Dependencies!$Q$3:$Q$502,0)),"") | D50: =IFERROR(INDEX(Dependencies!$G$3:$G$502,MATCH($A50,Dependencies!$Q$3:$Q$502,0)),"") | E50: =IFERROR(INDEX(Dependencies!$I$3:$I$502,MATCH($A50,Dependencies!$Q$3:$Q$502,0)),"") | F50: =IFERROR(INDEX(Dependencies!$J$3:$J$502,MATCH($A50,Dependencies!$Q$3:$Q$502,0)),"") | G50: =IFERROR(INDEX(Dependencies!$L$3:$L$502,MATCH($A50,Dependencies!$Q$3:$Q$502,0)),"") | H50: =IFERROR(INDEX(Dependencies!$K$3:$K$502,MATCH($A50,Dependencies!$Q$3:$Q$502,0)),"")
... A63: 25 | B63: =IFERROR(INDEX(Dependencies!$H$3:$H$502,MATCH($A63,Dependencies!$Q$3:$Q$502,0)),"") | C63: =IFERROR(INDEX(Dependencies!$E$3:$E$502,MATCH($A63,Dependencies!$Q$3:$Q$502,0)),"") | D63: =IFERROR(INDEX(Dependencies!$G$3:$G$502,MATCH($A63,Dependencies!$Q$3:$Q$502,0)),"") | E63: =IFERROR(INDEX(Dependencies!$I$3:$I$502,MATCH($A63,Dependencies!$Q$3:$Q$502,0)),"") | F63: =IFERROR(INDEX(Dependencies!$J$3:$J$502,MATCH($A63,Dependencies!$Q$3:$Q$502,0)),"") | G63: =IFERROR(INDEX(Dependencies!$L$3:$L$502,MATCH($A63,Dependencies!$Q$3:$Q$502,0)),"") | H63: =IFERROR(INDEX(Dependencies!$K$3:$K$502,MATCH($A63,Dependencies!$Q$3:$Q$502,0)),"")
A64: Shows first 25 matches per list. If B5 or B6 > 25, filter the Dependencies sheet directly.

Sheet Risks
A1: RISK / TECHNICAL DEBT REGISTER - Overall Risk is automatic: Likelihood (1-3) x Severity (1-4): >=9 Critical, 6-8 High, 3-5 Medium, 1-2 Low. Rows marked 'Suspected' are prompts to verify, not findings.
A2: Risk ID | B2: Date Discovered | C2: Component | D2: Risk Description | E2: Business Impact | F2: Technical Impact | G2: Likelihood | H2: Severity | I2: Overall Risk (auto) | J2: Owner | K2: Recommended Action | L2: Status | M2: Target Date | N2: Mitigation | O2: Evidence | P2: Related Object ID | Q2: Access Needed to Verify | R2: Notes
A3: R-001 | C3: Platform / staffing | D3: Sole administrator dependency has materialized: previous administrator left | E3: No known owner for platform changes or break-fix | F3: Undocumented configuration; unknown customizations | G3: High | H3: High | I3: =IF(OR(G3="",H3=""),"",IF(MATCH(G3,{"Low","Medium","High"},0)*MATCH(H3,{"Low","Medium","High","Critical"},0)>=9,"Critical",IF(MATCH(G3,{"Low","Medium","High"},0)*MATCH(H3,{"Low","Medium","High","Critical"},0)>=6,"High",IF(MATCH(G3,{"Low","Medium","High"},0)*MATCH(H3,{"Low","Medium","High","Critical"},0)>=3,"Medium","Low")))) -> Critical | K3: Establish platform owner, backup admin, escalation path (see Transition Checklist) | L3: Open | O3: Stated by workbook owner at project start | R3: Real entry - not an example. Add date.
A4: R-002 | C4: Access | D4: Current access is limited; may be asked to fix issues without access to inspect or change configuration | E4: Delayed resolution; accountability without authority | G4: High | H4: Medium | I4: =IF(OR(G4="",H4=""),"",IF(MATCH(G4,{"Low","Medium","High"},0)*MATCH(H4,{"Low","Medium","High","Critical"},0)>=9,"Critical",IF(MATCH(G4,{"Low","Medium","High"},0)*MATCH(H4,{"Low","Medium","High","Critical"},0)>=6,"High",IF(MATCH(G4,{"Low","Medium","High"},0)*MATCH(H4,{"Low","Medium","High","Critical"},0)>=3,"Medium","Low")))) -> High | K4: Use Access Roadmap to request access tied to specific responsibilities | L4: Open | O4: Stated by workbook owner | R4: Real entry - not an example.
A5: R-003 | C5: Unknown customizations | D5: HYPOTHESIS TO CHECK: Customized OOTB or custom objects exist with no documented purpose | I5: =IF(OR(G5="",H5=""),"",IF(MATCH(G5,{"Low","Medium","High"},0)*MATCH(H5,{"Low","Medium","High","Critical"},0)>=9,"Critical",IF(MATCH(G5,{"Low","Medium","High"},0)*MATCH(H5,{"Low","Medium","High","Critical"},0)>=6,"High",IF(MATCH(G5,{"Low","Medium","High"},0)*MATCH(H5,{"Low","Medium","High","Critical"},0)>=3,"Medium","Low")))) | L5: Suspected | R5: Assumption: common in inherited instances. Not evidence about YOUR instance. Verify, then set Likelihood/Severity and Status=Open, or Close.
A6: R-004 | C6: No documented integrations | D6: HYPOTHESIS TO CHECK: Inbound/outbound connections exist that nobody has inventoried | I6: =IF(OR(G6="",H6=""),"",IF(MATCH(G6,{"Low","Medium","High"},0)*MATCH(H6,{"Low","Medium","High","Critical"},0)>=9,"Critical",IF(MATCH(G6,{"Low","Medium","High"},0)*MATCH(H6,{"Low","Medium","High","Critical"},0)>=6,"High",IF(MATCH(G6,{"Low","Medium","High"},0)*MATCH(H6,{"Low","Medium","High","Critical"},0)>=3,"Medium","Low")))) | L6: Suspected | R6: Assumption: common in inherited instances. Not evidence about YOUR instance. Verify, then set Likelihood/Severity and Status=Open, or Close.
A7: R-005 | C7: Hard-coded logic | D7: HYPOTHESIS TO CHECK: Scripts or flows contain sys_ids, user/group names, emails, or URLs | I7: =IF(OR(G7="",H7=""),"",IF(MATCH(G7,{"Low","Medium","High"},0)*MATCH(H7,{"Low","Medium","High","Critical"},0)>=9,"Critical",IF(MATCH(G7,{"Low","Medium","High"},0)*MATCH(H7,{"Low","Medium","High","Critical"},0)>=6,"High",IF(MATCH(G7,{"Low","Medium","High"},0)*MATCH(H7,{"Low","Medium","High","Critical"},0)>=3,"Medium","Low")))) | L7: Suspected | R7: Assumption: common in inherited instances. Not evidence about YOUR instance. Verify, then set Likelihood/Severity and Status=Open, or Close.
A8: R-006 | C8: Scripts with unclear purpose | D8: HYPOTHESIS TO CHECK: Business rules/script includes nobody can explain | I8: =IF(OR(G8="",H8=""),"",IF(MATCH(G8,{"Low","Medium","High"},0)*MATCH(H8,{"Low","Medium","High","Critical"},0)>=9,"Critical",IF(MATCH(G8,{"Low","Medium","High"},0)*MATCH(H8,{"Low","Medium","High","Critical"},0)>=6,"High",IF(MATCH(G8,{"Low","Medium","High"},0)*MATCH(H8,{"Low","Medium","High","Critical"},0)>=3,"Medium","Low")))) | L8: Suspected | R8: Assumption: common in inherited instances. Not evidence about YOUR instance. Verify, then set Likelihood/Severity and Status=Open, or Close.
A9: R-007 | C9: Inactive former-employee accounts | D9: HYPOTHESIS TO CHECK: Departed staff still own records, integrations, jobs, or hold roles | I9: =IF(OR(G9="",H9=""),"",IF(MATCH(G9,{"Low","Medium","High"},0)*MATCH(H9,{"Low","Medium","High","Critical"},0)>=9,"Critical",IF(MATCH(G9,{"Low","Medium","High"},0)*MATCH(H9,{"Low","Medium","High","Critical"},0)>=6,"High",IF(MATCH(G9,{"Low","Medium","High"},0)*MATCH(H9,{"Low","Medium","High","Critical"},0)>=3,"Medium","Low")))) | L9: Suspected | R9: Assumption: common in inherited instances. Not evidence about YOUR instance. Verify, then set Likelihood/Severity and Status=Open, or Close.
A10: R-008 | C10: Excessive permissions | D10: HYPOTHESIS TO CHECK: Too many users/groups hold admin or powerful roles | I10: =IF(OR(G10="",H10=""),"",IF(MATCH(G10,{"Low","Medium","High"},0)*MATCH(H10,{"Low","Medium","High","Critical"},0)>=9,"Critical",IF(MATCH(G10,{"Low","Medium","High"},0)*MATCH(H10,{"Low","Medium","High","Critical"},0)>=6,"High",IF(MATCH(G10,{"Low","Medium","High"},0)*MATCH(H10,{"Low","Medium","High","Critical"},0)>=3,"Medium","Low")))) | L10: Suspected | R10: Assumption: common in inherited instances. Not evidence about YOUR instance. Verify, then set Likelihood/Severity and Status=Open, or Close.
A11: R-009 | C11: Critical workflows with no monitoring | D11: HYPOTHESIS TO CHECK: Flow or integration failures would go unnoticed | I11: =IF(OR(G11="",H11=""),"",IF(MATCH(G11,{"Low","Medium","High"},0)*MATCH(H11,{"Low","Medium","High","Critical"},0)>=9,"Critical",IF(MATCH(G11,{"Low","Medium","High"},0)*MATCH(H11,{"Low","Medium","High","Critical"},0)>=6,"High",IF(MATCH(G11,{"Low","Medium","High"},0)*MATCH(H11,{"Low","Medium","High","Critical"},0)>=3,"Medium","Low")))) | L11: Suspected | R11: Assumption: common in inherited instances. Not evidence about YOUR instance. Verify, then set Likelihood/Severity and Status=Open, or Close.
A12: R-010 | C12: No error handling | D12: HYPOTHESIS TO CHECK: Flows/scripts fail silently or leave records in limbo | I12: =IF(OR(G12="",H12=""),"",IF(MATCH(G12,{"Low","Medium","High"},0)*MATCH(H12,{"Low","Medium","High","Critical"},0)>=9,"Critical",IF(MATCH(G12,{"Low","Medium","High"},0)*MATCH(H12,{"Low","Medium","High","Critical"},0)>=6,"High",IF(MATCH(G12,{"Low","Medium","High"},0)*MATCH(H12,{"Low","Medium","High","Critical"},0)>=3,"Medium","Low")))) | L12: Suspected | R12: Assumption: common in inherited instances. Not evidence about YOUR instance. Verify, then set Likelihood/Severity and Status=Open, or Close.
A13: R-011 | C13: Manual workarounds | D13: HYPOTHESIS TO CHECK: People compensate for broken or missing automation | I13: =IF(OR(G13="",H13=""),"",IF(MATCH(G13,{"Low","Medium","High"},0)*MATCH(H13,{"Low","Medium","High","Critical"},0)>=9,"Critical",IF(MATCH(G13,{"Low","Medium","High"},0)*MATCH(H13,{"Low","Medium","High","Critical"},0)>=6,"High",IF(MATCH(G13,{"Low","Medium","High"},0)*MATCH(H13,{"Low","Medium","High","Critical"},0)>=3,"Medium","Low")))) | L13: Suspected | R13: Assumption: common in inherited instances. Not evidence about YOUR instance. Verify, then set Likelihood/Severity and Status=Open, or Close.
A14: R-012 | C14: Customized OOTB functionality | D14: HYPOTHESIS TO CHECK: Upgrade will collide with changes to OOTB objects | I14: =IF(OR(G14="",H14=""),"",IF(MATCH(G14,{"Low","Medium","High"},0)*MATCH(H14,{"Low","Medium","High","Critical"},0)>=9,"Critical",IF(MATCH(G14,{"Low","Medium","High"},0)*MATCH(H14,{"Low","Medium","High","Critical"},0)>=6,"High",IF(MATCH(G14,{"Low","Medium","High"},0)*MATCH(H14,{"Low","Medium","High","Critical"},0)>=3,"Medium","Low")))) | L14: Suspected | R14: Assumption: common in inherited instances. Not evidence about YOUR instance. Verify, then set Likelihood/Severity and Status=Open, or Close.
A15: R-013 | C15: No test coverage | D15: HYPOTHESIS TO CHECK: No ATF or documented regression tests for critical processes | I15: =IF(OR(G15="",H15=""),"",IF(MATCH(G15,{"Low","Medium","High"},0)*MATCH(H15,{"Low","Medium","High","Critical"},0)>=9,"Critical",IF(MATCH(G15,{"Low","Medium","High"},0)*MATCH(H15,{"Low","Medium","High","Critical"},0)>=6,"High",IF(MATCH(G15,{"Low","Medium","High"},0)*MATCH(H15,{"Low","Medium","High","Critical"},0)>=3,"Medium","Low")))) | L15: Suspected | R15: Assumption: common in inherited instances. Not evidence about YOUR instance. Verify, then set Likelihood/Severity and Status=Open, or Close.
A16: R-014 | C16: No change documentation | D16: HYPOTHESIS TO CHECK: No record of who changed what and why | I16: =IF(OR(G16="",H16=""),"",IF(MATCH(G16,{"Low","Medium","High"},0)*MATCH(H16,{"Low","Medium","High","Critical"},0)>=9,"Critical",IF(MATCH(G16,{"Low","Medium","High"},0)*MATCH(H16,{"Low","Medium","High","Critical"},0)>=6,"High",IF(MATCH(G16,{"Low","Medium","High"},0)*MATCH(H16,{"Low","Medium","High","Critical"},0)>=3,"Medium","Low")))) | L16: Suspected | R16: Assumption: common in inherited instances. Not evidence about YOUR instance. Verify, then set Likelihood/Severity and Status=Open, or Close.
... A20: R-018 | C20: Expiring credentials/certificates | D20: HYPOTHESIS TO CHECK: Integration credentials or certificates owned by departed staff | I20: =IF(OR(G20="",H20=""),"",IF(MATCH(G20,{"Low","Medium","High"},0)*MATCH(H20,{"Low","Medium","High","Critical"},0)>=9,"Critical",IF(MATCH(G20,{"Low","Medium","High"},0)*MATCH(H20,{"Low","Medium","High","Critical"},0)>=6,"High",IF(MATCH(G20,{"Low","Medium","High"},0)*MATCH(H20,{"Low","Medium","High","Critical"},0)>=3,"Medium","Low")))) | L20: Suspected | R20: Assumption: common in inherited instances. Not evidence about YOUR instance. Verify, then set Likelihood/Severity and Status=Open, or Close.
A21: EX-R-001 | C21: EX Set Cost Center Default | D21: Business rule has hard-coded group sys_id | E21: Wrong approver if group is replaced | G21: Medium | H21: High | I21: =IF(OR(G21="",H21=""),"",IF(MATCH(G21,{"Low","Medium","High"},0)*MATCH(H21,{"Low","Medium","High","Critical"},0)>=9,"Critical",IF(MATCH(G21,{"Low","Medium","High"},0)*MATCH(H21,{"Low","Medium","High","Critical"},0)>=6,"High",IF(MATCH(G21,{"Low","Medium","High"},0)*MATCH(H21,{"Low","Medium","High","Critical"},0)>=3,"Medium","Low")))) -> High | K21: Replace with property/lookup | L21: Open | O21: Fictional | P21: EX-SCR-001 | R21: EXAMPLE - FICTIONAL. Not part of your environment. Delete when you no longer need it.
I22: =IF(OR(G22="",H22=""),"",IF(MATCH(G22,{"Low","Medium","High"},0)*MATCH(H22,{"Low","Medium","High","Critical"},0)>=9,"Critical",IF(MATCH(G22,{"Low","Medium","High"},0)*MATCH(H22,{"Low","Medium","High","Critical"},0)>=6,"High",IF(MATCH(G22,{"Low","Medium","High"},0)*MATCH(H22,{"Low","Medium","High","Critical"},0)>=3,"Medium","Low"))))
I23: =IF(OR(G23="",H23=""),"",IF(MATCH(G23,{"Low","Medium","High"},0)*MATCH(H23,{"Low","Medium","High","Critical"},0)>=9,"Critical",IF(MATCH(G23,{"Low","Medium","High"},0)*MATCH(H23,{"Low","Medium","High","Critical"},0)>=6,"High",IF(MATCH(G23,{"Low","Medium","High"},0)*MATCH(H23,{"Low","Medium","High","Critical"},0)>=3,"Medium","Low"))))
I24: =IF(OR(G24="",H24=""),"",IF(MATCH(G24,{"Low","Medium","High"},0)*MATCH(H24,{"Low","Medium","High","Critical"},0)>=9,"Critical",IF(MATCH(G24,{"Low","Medium","High"},0)*MATCH(H24,{"Low","Medium","High","Critical"},0)>=6,"High",IF(MATCH(G24,{"Low","Medium","High"},0)*MATCH(H24,{"Low","Medium","High","Critical"},0)>=3,"Medium","Low"))))
I25: =IF(OR(G25="",H25=""),"",IF(MATCH(G25,{"Low","Medium","High"},0)*MATCH(H25,{"Low","Medium","High","Critical"},0)>=9,"Critical",IF(MATCH(G25,{"Low","Medium","High"},0)*MATCH(H25,{"Low","Medium","High","Critical"},0)>=6,"High",IF(MATCH(G25,{"Low","Medium","High"},0)*MATCH(H25,{"Low","Medium","High","Critical"},0)>=3,"Medium","Low"))))
I26: =IF(OR(G26="",H26=""),"",IF(MATCH(G26,{"Low","Medium","High"},0)*MATCH(H26,{"Low","Medium","High","Critical"},0)>=9,"Critical",IF(MATCH(G26,{"Low","Medium","High"},0)*MATCH(H26,{"Low","Medium","High","Critical"},0)>=6,"High",IF(MATCH(G26,{"Low","Medium","High"},0)*MATCH(H26,{"Low","Medium","High","Critical"},0)>=3,"Medium","Low"))))
I27: =IF(OR(G27="",H27=""),"",IF(MATCH(G27,{"Low","Medium","High"},0)*MATCH(H27,{"Low","Medium","High","Critical"},0)>=9,"Critical",IF(MATCH(G27,{"Low","Medium","High"},0)*MATCH(H27,{"Low","Medium","High","Critical"},0)>=6,"High",IF(MATCH(G27,{"Low","Medium","High"},0)*MATCH(H27,{"Low","Medium","High","Critical"},0)>=3,"Medium","Low"))))
I28: =IF(OR(G28="",H28=""),"",IF(MATCH(G28,{"Low","Medium","High"},0)*MATCH(H28,{"Low","Medium","High","Critical"},0)>=9,"Critical",IF(MATCH(G28,{"Low","Medium","High"},0)*MATCH(H28,{"Low","Medium","High","Critical"},0)>=6,"High",IF(MATCH(G28,{"Low","Medium","High"},0)*MATCH(H28,{"Low","Medium","High","Critical"},0)>=3,"Medium","Low"))))
I29: =IF(OR(G29="",H29=""),"",IF(MATCH(G29,{"Low","Medium","High"},0)*MATCH(H29,{"Low","Medium","High","Critical"},0)>=9,"Critical",IF(MATCH(G29,{"Low","Medium","High"},0)*MATCH(H29,{"Low","Medium","High","Critical"},0)>=6,"High",IF(MATCH(G29,{"Low","Medium","High"},0)*MATCH(H29,{"Low","Medium","High","Critical"},0)>=3,"Medium","Low"))))
I30: =IF(OR(G30="",H30=""),"",IF(MATCH(G30,{"Low","Medium","High"},0)*MATCH(H30,{"Low","Medium","High","Critical"},0)>=9,"Critical",IF(MATCH(G30,{"Low","Medium","High"},0)*MATCH(H30,{"Low","Medium","High","Critical"},0)>=6,"High",IF(MATCH(G30,{"Low","Medium","High"},0)*MATCH(H30,{"Low","Medium","High","Critical"},0)>=3,"Medium","Low"))))
I31: =IF(OR(G31="",H31=""),"",IF(MATCH(G31,{"Low","Medium","High"},0)*MATCH(H31,{"Low","Medium","High","Critical"},0)>=9,"Critical",IF(MATCH(G31,{"Low","Medium","High"},0)*MATCH(H31,{"Low","Medium","High","Critical"},0)>=6,"High",IF(MATCH(G31,{"Low","Medium","High"},0)*MATCH(H31,{"Low","Medium","High","Critical"},0)>=3,"Medium","Low"))))
I32: =IF(OR(G32="",H32=""),"",IF(MATCH(G32,{"Low","Medium","High"},0)*MATCH(H32,{"Low","Medium","High","Critical"},0)>=9,"Critical",IF(MATCH(G32,{"Low","Medium","High"},0)*MATCH(H32,{"Low","Medium","High","Critical"},0)>=6,"High",IF(MATCH(G32,{"Low","Medium","High"},0)*MATCH(H32,{"Low","Medium","High","Critical"},0)>=3,"Medium","Low"))))
I33: =IF(OR(G33="",H33=""),"",IF(MATCH(G33,{"Low","Medium","High"},0)*MATCH(H33,{"Low","Medium","High","Critical"},0)>=9,"Critical",IF(MATCH(G33,{"Low","Medium","High"},0)*MATCH(H33,{"Low","Medium","High","Critical"},0)>=6,"High",IF(MATCH(G33,{"Low","Medium","High"},0)*MATCH(H33,{"Low","Medium","High","Critical"},0)>=3,"Medium","Low"))))
... I502: =IF(OR(G502="",H502=""),"",IF(MATCH(G502,{"Low","Medium","High"},0)*MATCH(H502,{"Low","Medium","High","Critical"},0)>=9,"Critical",IF(MATCH(G502,{"Low","Medium","High"},0)*MATCH(H502,{"Low","Medium","High","Critical"},0)>=6,"High",IF(MATCH(G502,{"Low","Medium","High"},0)*MATCH(H502,{"Low","Medium","High","Critical"},0)>=3,"Medium","Low"))))

Sheet Unknowns
A1: UNKNOWNS - the antidote to guessing. Write the question, never a made-up answer. Seeded rows are real questions that apply to almost any inherited instance; answer them for YOUR instance.
A2: Unknown ID | B2: Question | C2: Related Object / ID | D2: Why It Matters | E2: Investigation Method | F2: Access Needed | G2: Who To Ask (SME) | H2: Owner | I2: Priority | J2: Status | K2: Answer | L2: Evidence / Source | M2: Date Raised | N2: Date Resolved | O2: Confidence
A3: U-001 | B3: Who is the platform owner and who is the business owner for ServiceNow overall? | D3: Decisions and escalations have no home | E3: Ask manager/CIO office; check ServiceNow contract/Now Support contacts | F3: Basic User | I3: Critical | J3: Open | O3: Unknown
A4: U-002 | B4: Who are the current administrators (including vendor/partner support)? | D4: Defines who can actually make and deploy changes | E4: User admin list (needs access) or ask security/IT | F4: Admin | I4: Critical | J4: Open | O4: Unknown
A5: U-003 | B5: Which instances exist (prod, test, dev) and which one is development done in? | D5: Changes in the wrong place can hit production | E5: Ask; check instance URLs; look for clone dates in sub-prod | F5: Basic User | I5: Critical | J5: Open | O5: Unknown
A6: U-004 | B6: How are changes moved to production today (update sets, pipeline, direct edits)? | D6: Defines change risk and who needs deploy rights | E6: Ask SMEs; later review update sets/versions | F6: Admin | I6: High | J6: Open | O6: Unknown
A7: U-005 | B7: What is the ServiceNow version and when was the last/next upgrade? | D7: Upgrade risk and customization compatibility | E7: Instance info page / ask platform owner / Now Support | F7: Basic User | I7: High | J7: Open | O7: Unknown
A8: U-006 | B8: What integrations exist, who owns each external system, and who holds the credentials? | D8: Silent breakage when credentials/certs expire | E8: Ask app owners; review REST messages, import sets, MID, scheduled jobs (needs access) | F8: Admin | I8: Critical | J8: Open | O8: Unknown
A9: U-007 | B9: Which scheduled jobs run, and what business process depends on each? | D9: Failed jobs may stop processes without warning | E9: Review scheduled jobs list; correlate with owners | F9: Admin | I9: High | J9: Open | O9: Unknown
A10: U-008 | B10: Is there existing documentation, update-set history, or a handoff note from the former administrator? | D10: Fastest source of 'why' | E10: Search shared drives, email, tickets, wiki; ask HR/manager for handoff material | F10: Basic User | I10: High | J10: Open | O10: Unknown
A11: U-009 | B11: Which user accounts own records, jobs, or integrations and are inactive/departed? | D11: Orphaned ownership | E11: Reports on inactive users with assignments (needs access) | F11: Admin | I11: High | J11: Open | O11: Unknown
A12: U-010 | B12: What testing exists for critical processes (ATF, manual scripts)? | D12: Determines how safely changes can be made | E12: Ask; review ATF suites if available | F12: Elevated Application | I12: Medium | J12: Open | O12: Unknown
A13: U-011 | B13: What am I formally expected to own, with what authority and access? | D13: Avoid ownership without authority | E13: Transition Checklist conversation with manager | F13: Basic User | I13: Critical | J13: Open | O13: Unknown
A14: U-012 | B14: Which 3-5 business processes matter most and who owns each? | D14: Focuses discovery on real work | E14: Stakeholder interviews | F14: Basic User | I14: Critical | J14: Open | O14: Unknown
A15: EX-U-001 | B15: EXAMPLE: Why does 'EX Set Cost Center Default' exist? | C15: EX-SCR-001 | D15: Might be required by Finance; removal could break reporting | E15: Check script comments, update set description, ask Finance and former team | F15: Admin | I15: Medium | J15: Open | K15: (not answered - do not invent) | L15: EXAMPLE - FICTIONAL. Not part of your environment. Delete when you no longer need it. | O15: Unknown

Sheet Decisions
A1: ARCHITECTURE DECISION LOG - record NEW decisions here. If you discover an OLD decision, record it as 'Reconstructed' and keep confidence honest: you are recording what you can prove, not guessing the reason.
A2: Decision ID | B2: Date | C2: Origin | D2: Problem | E2: Context | F2: Options Considered | G2: Decision | H2: Why | I2: Impact | J2: Objects Affected | K2: Risks | L2: Rollback | M2: Approver | N2: Review Date | O2: Status | P2: Confidence | Q2: Evidence / Source
A3: EX-D-001 | C3: New decision | D3: Approvals duplicated across flows | E3: Three flows each built their own approval steps | F3: A) copy logic B) shared subflow C) leave as is | G3: Use shared subflow 'EX Get Manager Approval' | H3: One place to fix approver logic | I3: Fewer places to maintain | J3: EX Laptop Request Fulfillment; EX Get Manager Approval | K3: Subflow change affects all callers | L3: Restore previous flow versions | M3: (example) Platform Owner | O3: Proposed | P3: High | Q3: EXAMPLE - FICTIONAL. Not part of your environment. Delete when you no longer need it.

Sheet Change History
A1: CHANGE HISTORY - changes YOU or your team make from now on. Do not backfill history you cannot prove; use Decisions (Reconstructed) or Unknowns for that.
A2: Change ID | B2: Date | C2: Change | D2: Reason | E2: Requestor | F2: Implementer | G2: Objects Affected | H2: Testing | I2: Approval | J2: Production Date | K2: Result | L2: Rollback | M2: Follow-up | N2: Ticket / Update Set | O2: Notes
A3: EX-C-001 | C3: Moved approver lookup into subflow | D3: See EX-D-001 | E3: (example) | F3: (example) | G3: EX Laptop Request Fulfillment | H3: Submitted 3 test requests in sub-prod | I3: (example) Platform Owner | K3: Success | L3: Restore flow v3 | O3: EXAMPLE - FICTIONAL. Not part of your environment. Delete when you no longer need it.

Sheet 30-Day Plan
A1: 30-DAY DISCOVERY PLAN - phases not heroics. If a day slips, move on; the goal is a defensible picture, not completeness.
A2: Day | B2: Phase | C2: Focus | D2: What To Do | E2: Output | F2: Workbook Sheet | G2: Typical Access Needed | H2: Status | I2: Date Done | J2: Notes | L2: Days done: | M2: =COUNTIF(H3:H32,"Done")&" / 30" -> 0 / 30
A3: 1 | B3: 1-3 Establish the perimeter | C3: Instances & your access | D3: Record prod and sub-prod URLs. Log in to each. Write down what you CAN open (catalog, lists, reports, knowledge) and what is blocked. Capture your own roles if visible; otherwise ask. | E3: Architecture Overview rows (instance, URL, prod/sub-prod); Unknowns for blanks | F3: Architecture Overview | G3: Basic User | H3: Not Started
A4: 2 | B4: 1-3 Establish the perimeter | C4: People & documentation | D4: List: platform owner, admins (incl. vendors), backup, security contact, business owners. Hunt existing docs: shared drives, wiki, email, handoff notes, tickets. Start Transition Checklist conversation with your manager. | E4: Contact list in Architecture Overview; U-001, U-002, U-008 updated; Transition Checklist started | F4: Transition Checklist | G4: Basic User | H4: Not Started
A5: 3 | B5: 1-3 Establish the perimeter | C5: Processes, systems, upgrade & dev/test process | D5: List 5-10 candidate business processes and their owners; list external systems you hear about; find out upgrade schedule and how changes reach production. Score candidates (volume, criticality, pain, SME availability). Do NOT try to understand everything. | E5: Business Processes rows (Priority to Trace set); Unknowns for dev/test, upgrades | F5: Business Processes | G5: Basic User | H5: Not Started
A6: 4 | B6: 4-7 Platform inventory | C6: Applications & modules | D6: Walk the application navigator. For each app/module: name, scope if visible, who uses it. Add to Applications and Object Inventory. | E6: Applications + Object Inventory rows | F6: Applications | G6: Basic User | H6: Not Started
A7: 5 | B7: 4-7 Platform inventory | C7: Catalogs & catalog items | D7: Browse the portal/catalog as a requester. Record catalogs, categories, items, visible variables, who owns each. Note items you cannot see (Access Needed). | E7: Catalog Items rows | F7: Catalog Items | G7: Basic User | H7: Not Started
A8: 6 | B8: 4-7 Platform inventory | C8: Tables, roles, groups, reports | D8: From forms/lists you can open, record table names and key fields. Record visible groups/roles, reports and dashboards, knowledge bases. | E8: Tables, Security, Object Inventory rows | F8: Tables | G8: Basic User | H8: Not Started
A9: 7 | B9: 4-7 Platform inventory | C9: Flows, scripts, integrations, jobs - and what you could not see | D9: Record anything visible; for everything else create an inventory row with Access Needed set. Draft your first access request from those rows. Review: counts on Dashboard. | E9: Access Roadmap requests drafted; Dashboard snapshot | F9: Dashboard | G9: Elevated Application | H9: Not Started
A10: 8 | B10: 8-14 Business process tracing | C10: Choose processes & kickoff | D10: Pick 3-5 processes. Book 30-45 minutes with each process owner: 'Show me how it works. Who does what? What breaks? What workarounds exist?' | E10: Process owners confirmed; interview notes | F10: Business Processes | G10: Basic User | H10: Not Started
A11: 9 | B11: 8-14 Business process tracing | C11: Process 1: user side | D11: Trace as the requester (use sub-prod and test records if allowed): catalog item, variables, visibility rules, what the user sees at each step. | E11: Variables rows; process steps draft | F11: Variables | G11: Basic User | H11: Not Started
A12: 10 | B12: 8-14 Business process tracing | C12: Process 1: back end | D12: Follow the records: tables, tasks, approvals, notifications, fields changed. Fill Business Processes row, link every object. Record Dependencies as you go. | E12: Tables/Flows/Dependencies rows linked to process | F12: Dependencies | G12: Elevated Application | H12: Not Started
A13: 11 | B13: 8-14 Business process tracing | C13: Process 2 | D13: Same trace. Note shared components (same flow, subflow, script include, table) - shared pieces are the highest-impact objects. | E13: Process 2 documented; shared objects flagged | F13: Business Processes | G13: Elevated Application | H13: Not Started
A14: 12 | B14: 8-14 Business process tracing | C14: Process 3 | D14: Same trace. | E14: Process 3 documented | F14: Business Processes | G14: Elevated Application | H14: Not Started
... A32: 30 | B32: 22-30 Validate & establish ownership | C32: Present | D32: Share Dashboard, top risks, traced processes, access request status, proposed ownership model, backlog. | E32: Presentation; agreed next steps | F32: Dashboard | G32: Basic User | H32: Not Started

Sheet Access Matrix
A1: ACCESS MATRIX - what each discovery item usually needs. ASSUMPTION: roles and ACLs vary by instance; treat 'minimum access' as a starting hypothesis and record what ACTUALLY blocked you.
A2: What You Want To Discover | B2: Typical Minimum Access (assumption) | C2: What Limits You | D2: Workaround With Less Access | E2: Set 'Access Needed' To | F2: Verified In My Instance?
A3: Catalog items you can request (names, descriptions, visible variables) | B3: Basic User | C3: Only items available to you via user criteria. Hidden items and technical names are not visible. | D3: Ask owners for item lists; screenshot the form | E3: Basic User
A4: Form field labels, list columns, choice values on tables you can read | B4: Basic User | C4: Labels yes; dictionary details (type/length/reference qualifier) usually need more. | D4: List > Export (if allowed) for visible data | E4: Basic User
A5: Reports, dashboards, knowledge bases shared with you | B5: Basic User | C5: Only shared ones; report definitions may be viewable only to some roles. | D5: Ask report owners for definitions | E5: Basic User
A6: Notifications you receive (sample emails) | B6: Basic User | C6: You see outputs, not conditions or recipients logic. | D6: Keep samples as evidence | E6: Basic User
A7: Approvals/tasks assigned to you; observed process behavior in test | B7: Basic User | C7: Test in sub-prod with permission only. | D7: Ask for test persona accounts | E7: Basic User
A8: Application navigator: apps and modules visible to you | B8: Basic User | C8: Shows only what your roles allow - absence is not proof of non-existence. | D8: Compare with a fulfiller's view | E8: Basic User
A9: Tables, columns, extends relationships (schema) | B9: Elevated Application | C9: Often restricted; some instances allow read of dictionary to analysts. Verify yours. | D9: Ask for dictionary export | E9: Elevated Application
A10: Roles/groups membership lists | B10: Elevated Application | C10: User/group admin visibility varies; may be read-only to some. | D10: Ask for export of role/group reports | E10: Elevated Application
A11: Flow Designer flows, subflows, actions, executions | B11: Elevated Application | C11: Flow Designer roles or admin typically needed to view; executions may be restricted. | D11: Ask flow owner for screenshots/export | E11: Elevated Application
A12: Business rules, client scripts, UI policies, UI actions | B12: Admin | C12: Script records are typically admin-readable; scoped apps may differ. | D12: Request read-only config access | E12: Admin
A13: Script includes and script content | B13: Admin | C13: Same. You need to read code to find hard-coded values. | D13: Read-only developer access in sub-prod | E13: Admin
A14: Scheduled jobs / scheduled flows | B14: Admin | C14: Job list and run history are often admin-only. | D14: Ask for job report | E14: Admin
... A23: Raw data exports at scale, ETL, direct DB reporting | B23: Database/Platform | C23: Often via approved reporting/data-export mechanisms. | D23: Use approved reports/exports | E23: Database/Platform

Sheet Access Roadmap
A1: ACCESS ROADMAP - capability first, role second. 'Typical access' is an ASSUMPTION: role names differ by instance. Record the real role/ticket in Notes. Ask for access TIED TO A RESPONSIBILITY, not generically.
A2: Level | B2: Capability Needed | C2: Why It Is Needed | D2: Typical ServiceNow Access (verify in your instance) | E2: Risk If Missing | F2: Temporary or Permanent | G2: Request Status | H2: Date Requested | I2: Approver | J2: Date Granted | K2: Notes / Actual Role or Ticket
A3: L1 Discovery | B3: Read/test the processes as a requester and fulfiller (sub-prod) | C3: See behavior without touching config | D3: Standard user + test persona accounts or a fulfiller role in sub-prod | E3: You trace only the happy path; cannot reproduce fulfiller issues | F3: Temporary then review | G3: Not Needed Yet
A4: L1 Discovery | B4: Read-only access to the business tables for traced processes | C4: Know what data exists and who changes it | D4: Table-specific read via role/ACL; or approved exports | E4: Process traces are incomplete; Unknowns pile up | F4: Permanent | G4: Not Needed Yet
A5: L1 Discovery | B5: Ability to export lists/reports you can read | C5: Capture inventory evidence | D5: Export-capable user role on reportable tables | E5: Manual copying; evidence quality drops | F5: Permanent | G5: Not Needed Yet
A6: L2 Application Analyst | B6: Read-only view of configuration (flows, rules, scripts, ACLs, jobs) in sub-prod | C6: Understand how it actually works; find hidden dependencies | D6: Often admin-level; ask for a custom read-only 'configuration viewer' role or sub-prod admin | E6: Cannot answer 'what breaks if I change this' | F6: Permanent (read-only) | G6: Not Needed Yet
A7: L2 Application Analyst | B7: View system logs, email logs, flow executions, import errors | C7: Troubleshoot instead of guess | D7: Admin-level or log-reader roles (varies) | E7: Break-fix is blind; escalations pile up | F7: Permanent (read-only) | G7: Not Needed Yet
A8: L2 Application Analyst | B8: Impersonate/test as users in sub-prod | C8: Reproduce user issues and validate fixes | D8: Impersonation role (audit-sensitive); prefer test accounts | E8: Cannot validate fixes; defects missed | F8: Temporary then review | G8: Not Needed Yet
A9: L2 Application Analyst | B9: Run/review automated tests (ATF) if used | C9: Regression safety | D9: ATF tester/admin roles (if ATF is in use) | E9: No safe way to verify changes | F9: Permanent | G9: Not Needed Yet
A10: L2 Application Analyst | B10: Read update sets / change history | C10: Find the 'why' and timeline | D10: Admin-level; request read-only | E10: Unknown history; more Unknowns | F10: Permanent (read-only) | G10: Not Needed Yet
A11: L3 Application Administrator | B11: Maintain catalog items, variables, UI policies for owned apps | C11: Make approved configuration changes | D11: Catalog admin/editor roles scoped to your catalogs | E11: Requests for simple changes stall | F11: Permanent | G11: Not Needed Yet
A12: L3 Application Administrator | B12: Create/edit flows and application scripts in sub-prod (scope-limited) | C12: Implement approved changes | D12: Flow Designer + scoped developer roles in sub-prod | E12: You carry accountability without ability to deliver | F12: Permanent (sub-prod) | G12: Not Needed Yet
A13: L3 Application Administrator | B13: Manage assignment groups and application role assignment | C13: Keep fulfillment working | D13: Group/user admin delegated to your app scope | E13: Fulfillment stalls waiting on others | F13: Permanent | G13: Not Needed Yet
A14: L3 Application Administrator | B14: Prepare, test, and promote changes via agreed process | C14: Deliver changes safely | D14: Update-set/pipeline permissions; production deploy may stay with platform admin | E14: Unclear who deploys; changes bypass control | F14: Permanent for sub-prod; production per policy | G14: Not Needed Yet
... A20: L4 Platform Administrator | B20: Raise/track Now Support cases | C20: Vendor escalation | D20: Named customer contact / support entitlement | E20: Escalations go nowhere | F20: Permanent | G20: Not Needed Yet

Sheet Responsibility Modes
A1: RESPONSIBILITY MODES - name which mode you are in before you accept a request. 'I can do X in Discovery/Troubleshooting mode; Configuration/Ownership needs Y.'
A2: Mode | B2: What It Means | C2: Typical Activities | D2: Authority Needed | E2: Access Needed | F2: What You Are NOT Agreeing To | G2: Red-flag Phrase | H2: Am I Operating In This Mode Today? (Y/N)
A3: Discovery | B3: Learning what exists and how it fits together; read-only. | C3: Inventory, tracing, interviews, documenting | D3: Access to observe; no authority to change | E3: Read-only/inspect (L1-L2) | F3: Fixes, outcomes, ownership | G3: 'Just have a look at it'
A4: Troubleshooting | B4: Finding the cause of a specific issue; may recommend a fix. | C4: Reproduce, read logs, isolate, report findings | D4: Authority to investigate and escalate; not to change prod | E4: Log/config read, sub-prod test (L2) | F4: Making the fix; owning the outcome | G4: 'Can you figure out why it's broken?'
A5: Configuration | B5: Making approved changes within defined scope. | C5: Catalog/flow/rule edits, per change process | D5: Authority within a defined scope and approved change | E5: L3 in sub-prod; deploy per process | F5: Platform-wide impact; production deployment unless stated | G5: 'Can you just update that?'
A6: Administration | B6: Operating the application: users, groups, config, health. | C6: Role assignment, monitoring, housekeeping | D6: Authority over application operations | E6: L3 plus agreed admin duties | F6: Platform architecture, security policy | G6: 'You're the admin now'
A7: Ownership | B7: Accountable for outcomes: availability, quality, risk acceptance. | C7: Owning roadmap, decisions, risk | D7: Decision rights and budget/priority influence | E7: Whatever delivery needs, plus backup | F7: Being blamed for pre-existing debt | G7: 'It's yours now'
A8: Production Support | B8: Keeping live processes running; incident response. | C8: Triage, workaround, escalate, restore | D8: Defined response hours/SLAs; production authority or escalation | E8: Production log/config access; break-glass process | F8: 24x7 coverage unless agreed | G8: 'Fix it now, whatever it takes'
A9: Project Work | B9: Planned changes with scope, time, testing, approval. | C9: Requirements, build, test, release | D9: Scope/schedule authority; change approval | E9: Sub-prod build; release via process | F9: Unscoped 'while you're in there' work | G9: 'Small tweak, shouldn't take long'
A10: Technical Leadership | B10: Setting standards, architecture direction, mentoring. | C10: Standards, reviews, decisions, onboarding | D10: Authority to set/enforce standards | E10: Broad read + review rights | F10: Unfunded platform strategy | G10: 'You know the most about it'

Sheet Transition Checklist
A1: OWNERSHIP / TRANSITION CHECKLIST - get answers in writing (email is fine) BEFORE accepting ongoing ownership. 'Not Asked' items are your homework.
A2: Category | B2: Question To Ask | C2: Evidence To Get | D2: Status | E2: Agreed Answer | F2: Agreed With | G2: Date | H2: Notes
A3: Responsibility | B3: What exactly am I being asked to do (discovery / troubleshooting / configuration / ownership)? | C3: Written scope in one or two sentences | D3: Not Asked
A4: Responsibility | B4: Which applications/processes are in scope, and which are explicitly out of scope? | C4: List of apps/processes | D4: Not Asked
A5: Responsibility | B5: Am I responsible for outcomes, or for effort and reporting? | C5: Wording agreed with manager | D5: Not Asked
A6: Responsibility | B6: Is this in addition to my current job? What is deprioritized? | C6: Capacity statement / priorities | D6: Not Asked
A7: Authority | B7: What can I decide alone? What needs approval? | C7: Decision rights list | D7: Not Asked
A8: Authority | B8: Who is accountable if a change causes an incident? | C8: Named person/role | D8: Not Asked
A9: Access | B9: What access do I have today, and what is needed for the agreed scope? | C9: Access Roadmap rows filled | D9: Not Asked
A10: Access | B10: Who grants access and how long does it take? | C10: Approver + SLA | D10: Not Asked
A11: Access | B11: Is access permanent or temporary? Is it audited? | C11: Agreement noted | D11: Not Asked
A12: Documentation | B12: Does handoff documentation from the former admin exist? Where? | C12: Location or 'none' | D12: Not Asked
A13: Documentation | B13: Where will documentation live and who may edit it? | C13: Location + standard | D13: Not Asked
A14: Documentation | B14: Are there known undocumented customizations? | C14: List or Unknown IDs | D14: Not Asked
... A38: Something Is Broken | B38: What do I record afterward? (Unknown, Risk, Decision, Change) | C38: Entries created | D38: Not Asked

Sheet Reference Lists
A1: ObjectType | B1: Status | C1: ActiveInactive | D1: OOTB | E1: Criticality | F1: DocStatus | G1: Confidence | H1: Access | I1: Priority | J1: Likelihood | K1: Severity | L1: RiskStatus | M1: UnknownStatus | N1: YesNoUnknown | O1: Direction | P1: Technology | Q1: Auth | R1: Relationship | S1: DepType | T1: DecisionStatus | U1: DecisionOrigin | V1: ChangeResult | W1: PlanStatus | X1: ScriptType | Y1: FlowType | Z1: SecType | AA1: ACLOp | AB1: FieldType | AC1: ReqStatus | AD1: TempPerm | AE1: ChecklistStatus | AF1: Level | AG1: Env | AI1: Definitions
A2: Table | B2: In Use | C2: Active | D2: OOTB | E2: Critical | F2: Not Started | G2: High | H2: Basic User | I2: Critical | J2: Low | K2: Low | L2: Suspected | M2: Open | N2: Yes | O2: Inbound | P2: REST | Q2: Basic | R2: reads from | S2: Data | T2: Proposed | U2: New decision | V2: Pending | W2: Not Started | X2: Business Rule | Y2: Flow | Z2: Role | AA2: read | AB2: String | AC2: Not Needed Yet | AD2: Temporary | AE2: Not Asked | AF2: L1 Discovery | AG2: Production | AI2: CONFIDENCE: High = verified directly in ServiceNow | Medium = strongly supported, not fully verified | Low = inferred, needs validation | Unknown = not checked
A3: Field | B3: Not In Use | C3: Inactive | D3: Customized OOTB | E3: High | F3: Discovered | G3: Medium | H3: Elevated Application | I3: High | J3: Medium | K3: Medium | L3: Open | M3: Investigating | N3: No | O3: Outbound | P3: SOAP | Q3: OAuth 2.0 | R3: writes to | S3: Automation | T3: Approved | U3: Reconstructed (inferred) | V3: Success | W3: In Progress | X3: Client Script | Y3: Subflow | Z3: Group | AA3: write | AB3: Integer | AC3: Planned | AD3: Permanent | AE3: Asked | AF3: L2 Application Analyst | AG3: Sub-production | AI3: CRITICALITY: Critical = process stops or compliance impact | High = major degradation | Medium = workaround exists | Low = minor
A4: Application | B4: Unknown | C4: Unknown | D4: Custom | E4: Medium | F4: Partially Documented | G4: Low | H4: Admin | I4: Medium | J4: High | K4: High | L4: Mitigating | M4: Blocked - Needs Access | N4: Unknown | O4: Bidirectional | P4: Import Set / Transform Map | Q4: API Key | R4: updates | S4: Code | T4: Implemented | U4: Reconstructed (confirmed by SME) | V4: Partial | W4: Done | X4: Script Include | Y4: Flow Action | Z4: ACL | AA4: create | AB4: Boolean | AC4: Requested | AD4: Temporary then review | AE4: Agreed | AF4: L3 Application Administrator | AG4: Both | AI4: RISK SCORE: Likelihood Low/Med/High = 1/2/3 times Severity Low/Med/High/Critical = 1/2/3/4. >=9 Critical, 6-8 High, 3-5 Medium, 1-2 Low
A5: Module | B5: Deprecated | D5: Unknown | E5: Low | F5: Documented | G5: Unknown | H5: Security Admin | I5: Low | K5: Critical | L5: Accepted | M5: Blocked - Needs SME | O5: Unknown | P5: MID Server | Q5: Certificate / mTLS | R5: creates records in | S5: Security | T5: Superseded | V5: Failed | W5: Skipped | X5: UI Action | Y5: Scheduled Flow | AA5: delete | AB5: Choice | AC5: Granted | AD5: Either | AE5: Partially Agreed | AF5: L4 Platform Administrator | AG5: Unknown | AI5: DOC STATUS: Documented = template complete. Validated = confirmed by direct check or SME. Dashboard counts both as documented.
A6: Flow | B6: Planned | E6: Unknown | F6: Validated | H6: Database/Platform | L6: Closed | M6: Resolved | P6: IntegrationHub / Spoke | Q6: SSO / SAML | R6: deletes from | S6: UI | T6: Reversed | V6: Rolled Back | W6: Blocked | X6: UI Script | Y6: Legacy Workflow | AA6: execute | AB6: Reference | AC6: Denied | AE6: Declined | AI6: ACCESS NEEDED: Basic User < Elevated Application < Admin < Security Admin < Database/Platform. Pick the LOWEST level that lets you verify the item.
A7: Subflow | F7: Needs Update | M7: Closed - Not Resolvable | P7: Email | Q7: None | R7: runs on | S7: Integration | X7: Scheduled Script | Y7: Other | AA7: report_view | AB7: List | AC7: Granted - Temporary | AE7: Not Applicable | AI7: EXAMPLES: Rows with IDs starting EX- are fictional and excluded from Dashboard counts. Delete them when you are comfortable.
A8: Flow Action | P8: SFTP / Flat File | Q8: Unknown | R8: launches | S8: Reporting | X8: Fix Script | AA8: other | AB8: Glide Date/Time | AI8: TO ADD A DROPDOWN VALUE: type it at the bottom of the list column (the dropdown range is fixed to the current length; insert a row INSIDE the list to extend it).
A9: Business Rule | P9: JDBC | R9: calls | S9: Configuration | X9: Script Action | AB9: Date
A10: Client Script | P10: SSO / SAML / LDAP | R10: called by | S10: Notification | X10: Scripted REST | AB10: Journal
A11: UI Policy | P11: Other | R11: triggers | S11: Other | X11: Transform Script | AB11: Script
A12: UI Action | P12: Unknown | R12: protects | X12: ACL Script | AB12: Currency
A13: Script Include | R13: requires role | X13: Other | AB13: Other
A14: ACL | R14: notifies
A15: Role | R15: requests approval from
A16: Group | R16: extends
A17: Catalog Item | R17: references
A18: Variable | R18: imports into
A19: Variable Set | R19: exports from
A20: Record Producer | R20: reports on
A21: Notification | R21: displays
A22: Scheduled Job | R22: member of
A23: Integration | R23: depends on
A24: REST API | R24: other
A25: Data Source
A26: Transform Map
A27: Report
A28: Dashboard
A29: Widget
A30: Portal
A31: Knowledge Base
A32: Other
